{
"meta":{"test_sets":[],"test_metrics":[],"learn_metrics":[{"best_value":"Min","name":"Logloss"}],"launch_mode":"Train","parameters":"","iteration_count":1000,"learn_sets":["learn"],"name":"experiment"},
"iterations":[
{"learn":[0.6409240251],"iteration":0,"passed_time":0.09601659321,"remaining_time":95.92057662},
{"learn":[0.5965036963],"iteration":1,"passed_time":0.1325995123,"remaining_time":66.16715666},
{"learn":[0.55894186],"iteration":2,"passed_time":0.1744113363,"remaining_time":57.96270075},
{"learn":[0.5270975374],"iteration":3,"passed_time":0.2119110583,"remaining_time":52.76585353},
{"learn":[0.5002318779],"iteration":4,"passed_time":0.2673935015,"remaining_time":53.21130679},
{"learn":[0.4776013514],"iteration":5,"passed_time":0.32297571,"remaining_time":53.50630928},
{"learn":[0.4582847795],"iteration":6,"passed_time":0.3743521444,"remaining_time":53.10452562},
{"learn":[0.4420662185],"iteration":7,"passed_time":0.4151973201,"remaining_time":51.48446769},
{"learn":[0.4283190695],"iteration":8,"passed_time":0.4648450627,"remaining_time":51.18460635},
{"learn":[0.4166306264],"iteration":9,"passed_time":0.5007245945,"remaining_time":49.57173486},
{"learn":[0.406688604],"iteration":10,"passed_time":0.5394640502,"remaining_time":48.50272233},
{"learn":[0.3981036515],"iteration":11,"passed_time":0.5519550377,"remaining_time":45.4442981},
{"learn":[0.3908728211],"iteration":12,"passed_time":0.5627223828,"remaining_time":42.72361476},
{"learn":[0.38468203],"iteration":13,"passed_time":0.5769585728,"remaining_time":40.63436806},
{"learn":[0.3794515332],"iteration":14,"passed_time":0.6010125134,"remaining_time":39.46648838},
{"learn":[0.3748914533],"iteration":15,"passed_time":0.6207126151,"remaining_time":38.17382583},
{"learn":[0.3710215843],"iteration":16,"passed_time":0.6343356258,"remaining_time":36.67952472},
{"learn":[0.3677054668],"iteration":17,"passed_time":0.6503069797,"remaining_time":35.47785856},
{"learn":[0.3648492389],"iteration":18,"passed_time":0.6775529811,"remaining_time":34.98313024},
{"learn":[0.3624277202],"iteration":19,"passed_time":0.7087218212,"remaining_time":34.72736924},
{"learn":[0.3603076386],"iteration":20,"passed_time":0.7374965229,"remaining_time":34.38138552},
{"learn":[0.3585351034],"iteration":21,"passed_time":0.769807292,"remaining_time":34.22143325},
{"learn":[0.3569208503],"iteration":22,"passed_time":0.798634243,"remaining_time":33.92459371},
{"learn":[0.3555202908],"iteration":23,"passed_time":0.8151249618,"remaining_time":33.14841511},
{"learn":[0.35434841],"iteration":24,"passed_time":0.8278866924,"remaining_time":32.287581},
{"learn":[0.3533292435],"iteration":25,"passed_time":0.8408075786,"remaining_time":31.49794544},
{"learn":[0.3524633953],"iteration":26,"passed_time":0.852635484,"remaining_time":30.72645651},
{"learn":[0.3516875427],"iteration":27,"passed_time":0.8673123225,"remaining_time":30.10812777},
{"learn":[0.3510228353],"iteration":28,"passed_time":0.8806539705,"remaining_time":29.48672432},
{"learn":[0.3504788863],"iteration":29,"passed_time":0.9076228248,"remaining_time":29.34647133},
{"learn":[0.3500080067],"iteration":30,"passed_time":0.9369293448,"remaining_time":29.28659791},
{"learn":[0.3495777458],"iteration":31,"passed_time":0.9815560885,"remaining_time":29.69207168},
{"learn":[0.3491966945],"iteration":32,"passed_time":1.019388068,"remaining_time":29.87115944},
{"learn":[0.3488001347],"iteration":33,"passed_time":1.061034935,"remaining_time":30.14587492},
{"learn":[0.348519243],"iteration":34,"passed_time":1.08953146,"remaining_time":30.03993882},
{"learn":[0.3482808807],"iteration":35,"passed_time":1.115936268,"remaining_time":29.88229341},
{"learn":[0.3480453889],"iteration":36,"passed_time":1.142661011,"remaining_time":29.74006902},
{"learn":[0.3477950066],"iteration":37,"passed_time":1.157502015,"remaining_time":29.30307733},
{"learn":[0.3476201376],"iteration":38,"passed_time":1.171531672,"remaining_time":28.86774196},
{"learn":[0.347442396],"iteration":39,"passed_time":1.197249153,"remaining_time":28.73397968},
{"learn":[0.3472769102],"iteration":40,"passed_time":1.229388486,"remaining_time":28.75569654},
{"learn":[0.347153681],"iteration":41,"passed_time":1.242417744,"remaining_time":28.33895711},
{"learn":[0.347049935],"iteration":42,"passed_time":1.254793197,"remaining_time":27.92644394},
{"learn":[0.3469757165],"iteration":43,"passed_time":1.271782542,"remaining_time":27.63236614},
{"learn":[0.3468752474],"iteration":44,"passed_time":1.290170506,"remaining_time":27.38028518},
{"learn":[0.3467881557],"iteration":45,"passed_time":1.310325372,"remaining_time":27.17500881},
{"learn":[0.3467152801],"iteration":46,"passed_time":1.33212792,"remaining_time":27.01101932},
{"learn":[0.346618897],"iteration":47,"passed_time":1.353816757,"remaining_time":26.85069901},
{"learn":[0.3465441125],"iteration":48,"passed_time":1.387816055,"remaining_time":26.93496058},
{"learn":[0.3465152887],"iteration":49,"passed_time":1.427628234,"remaining_time":27.12493645},
{"learn":[0.3464632945],"iteration":50,"passed_time":1.465696343,"remaining_time":27.27344763},
{"learn":[0.3464203953],"iteration":51,"passed_time":1.540214072,"remaining_time":28.07928731},
{"learn":[0.3463573213],"iteration":52,"passed_time":1.560809848,"remaining_time":27.88843257},
{"learn":[0.3463269301],"iteration":53,"passed_time":1.574265748,"remaining_time":27.57880366},
{"learn":[0.3462877848],"iteration":54,"passed_time":1.587803451,"remaining_time":27.2813502},
{"learn":[0.3462301515],"iteration":55,"passed_time":1.604888904,"remaining_time":27.05384153},
{"learn":[0.3461929982],"iteration":56,"passed_time":1.626177307,"remaining_time":26.90324913},
{"learn":[0.3461517484],"iteration":57,"passed_time":1.640415591,"remaining_time":26.64261184},
{"learn":[0.3461024095],"iteration":58,"passed_time":1.654710069,"remaining_time":26.39122331},
{"learn":[0.3460576348],"iteration":59,"passed_time":1.672276036,"remaining_time":26.19899123},
{"learn":[0.3460301468],"iteration":60,"passed_time":1.68552412,"remaining_time":25.94601883},
{"learn":[0.3459852606],"iteration":61,"passed_time":1.696467422,"remaining_time":25.66591035},
{"learn":[0.3459541423],"iteration":62,"passed_time":1.712020989,"remaining_time":25.46291535},
{"learn":[0.3459113707],"iteration":63,"passed_time":1.725078359,"remaining_time":25.229271},
{"learn":[0.3459072579],"iteration":64,"passed_time":1.733557362,"remaining_time":24.93655591},
{"learn":[0.3458775217],"iteration":65,"passed_time":1.747871838,"remaining_time":24.7350348},
{"learn":[0.3458567192],"iteration":66,"passed_time":1.774032252,"remaining_time":24.70406106},
{"learn":[0.3458359733],"iteration":67,"passed_time":1.788889616,"remaining_time":24.51831062},
{"learn":[0.3458046588],"iteration":68,"passed_time":1.802071247,"remaining_time":24.31490335},
{"learn":[0.3457781449],"iteration":69,"passed_time":1.815524903,"remaining_time":24.12054514},
{"learn":[0.3457419634],"iteration":70,"passed_time":1.8283656,"remaining_time":23.92326257},
{"learn":[0.3457245365],"iteration":71,"passed_time":1.841410096,"remaining_time":23.73373013},
{"learn":[0.3456997424],"iteration":72,"passed_time":1.856120167,"remaining_time":23.57018349},
{"learn":[0.3456827754],"iteration":73,"passed_time":1.870129102,"remaining_time":23.40188579},
{"learn":[0.3456794969],"iteration":74,"passed_time":1.884922317,"remaining_time":23.24737525},
{"learn":[0.3456585142],"iteration":75,"passed_time":1.913524208,"remaining_time":23.2644259},
{"learn":[0.3456381426],"iteration":76,"passed_time":1.940549891,"remaining_time":23.26139674},
{"learn":[0.3456268079],"iteration":77,"passed_time":1.969034173,"remaining_time":23.27499368},
{"learn":[0.3456158141],"iteration":78,"passed_time":2.000038026,"remaining_time":23.31689901},
{"learn":[0.3455681366],"iteration":79,"passed_time":2.027905562,"remaining_time":23.32091397},
{"learn":[0.3455351643],"iteration":80,"passed_time":2.057087992,"remaining_time":23.33906005},
{"learn":[0.3455210593],"iteration":81,"passed_time":2.083898053,"remaining_time":23.32949284},
{"learn":[0.3454944702],"iteration":82,"passed_time":2.110478218,"remaining_time":23.31697019},
{"learn":[0.3454726874],"iteration":83,"passed_time":2.139665927,"remaining_time":23.33254749},
{"learn":[0.3454453598],"iteration":84,"passed_time":2.167464395,"remaining_time":23.33211672},
{"learn":[0.34541648],"iteration":85,"passed_time":2.193682767,"remaining_time":23.31425638},
{"learn":[0.3453883521],"iteration":86,"passed_time":2.206704691,"remaining_time":23.15771704},
{"learn":[0.3453707861],"iteration":87,"passed_time":2.233580316,"remaining_time":23.14801419},
{"learn":[0.3453496875],"iteration":88,"passed_time":2.250435272,"remaining_time":23.0353543},
{"learn":[0.3453226659],"iteration":89,"passed_time":2.265696015,"remaining_time":22.90870416},
{"learn":[0.3453033281],"iteration":90,"passed_time":2.27448804,"remaining_time":22.71988603},
{"learn":[0.3452751511],"iteration":91,"passed_time":2.285880367,"remaining_time":22.56064536},
{"learn":[0.3452516584],"iteration":92,"passed_time":2.296935115,"remaining_time":22.40129193},
{"learn":[0.3452203189],"iteration":93,"passed_time":2.307905338,"remaining_time":22.2442791},
{"learn":[0.3452116395],"iteration":94,"passed_time":2.329875499,"remaining_time":22.19512975},
{"learn":[0.3451971201],"iteration":95,"passed_time":2.347227969,"remaining_time":22.10306337},
{"learn":[0.3451662193],"iteration":96,"passed_time":2.364185796,"remaining_time":22.00886364},
{"learn":[0.3451559426],"iteration":97,"passed_time":2.380532367,"remaining_time":21.91061423},
{"learn":[0.3451318338],"iteration":98,"passed_time":2.408741547,"remaining_time":21.92198115},
{"learn":[0.3451157633],"iteration":99,"passed_time":2.433631291,"remaining_time":21.90268162},
{"learn":[0.3451039671],"iteration":100,"passed_time":2.4490242,"remaining_time":21.79874016},
{"learn":[0.3450905309],"iteration":101,"passed_time":2.458949841,"remaining_time":21.64840154},
{"learn":[0.3450713985],"iteration":102,"passed_time":2.472214887,"remaining_time":21.52987139},
{"learn":[0.3450539235],"iteration":103,"passed_time":2.487940627,"remaining_time":21.4345654},
{"learn":[0.3450235376],"iteration":104,"passed_time":2.498093761,"remaining_time":21.29327539},
{"learn":[0.3450129353],"iteration":105,"passed_time":2.509577865,"remaining_time":21.16568501},
{"learn":[0.3450013398],"iteration":106,"passed_time":2.519405554,"remaining_time":21.02644075},
{"learn":[0.3449750773],"iteration":107,"passed_time":2.529634519,"remaining_time":20.89290732},
{"learn":[0.3449584567],"iteration":108,"passed_time":2.539361201,"remaining_time":20.75753055},
{"learn":[0.3449332528],"iteration":109,"passed_time":2.562294933,"remaining_time":20.73129537},
{"learn":[0.3449180048],"iteration":110,"passed_time":2.578825486,"remaining_time":20.65383655},
{"learn":[0.3449010037],"iteration":111,"passed_time":2.591070456,"remaining_time":20.54348719},
{"learn":[0.3448934944],"iteration":112,"passed_time":2.601890018,"remaining_time":20.42368536},
{"learn":[0.3448788555],"iteration":113,"passed_time":2.61214431,"remaining_time":20.30140227},
{"learn":[0.3448446677],"iteration":114,"passed_time":2.622186538,"remaining_time":20.17943553},
{"learn":[0.3448418499],"iteration":115,"passed_time":2.631496836,"remaining_time":20.05382071},
{"learn":[0.3448160403],"iteration":116,"passed_time":2.641325737,"remaining_time":19.93410791},
{"learn":[0.3448021099],"iteration":117,"passed_time":2.65158051,"remaining_time":19.81944076},
{"learn":[0.3447886189],"iteration":118,"passed_time":2.661169666,"remaining_time":19.70160064},
{"learn":[0.3447631354],"iteration":119,"passed_time":2.671292434,"remaining_time":19.58947785},
{"learn":[0.3447451528],"iteration":120,"passed_time":2.68109193,"remaining_time":19.47669262},
{"learn":[0.3447391115],"iteration":121,"passed_time":2.691071722,"remaining_time":19.36689321},
{"learn":[0.3447193193],"iteration":122,"passed_time":2.700846503,"remaining_time":19.25725515},
{"learn":[0.3447015884],"iteration":123,"passed_time":2.711332375,"remaining_time":19.1542513},
{"learn":[0.3446898901],"iteration":124,"passed_time":2.724305228,"remaining_time":19.07013659},
{"learn":[0.3446599801],"iteration":125,"passed_time":2.754768347,"remaining_time":19.1084725},
{"learn":[0.3446519729],"iteration":126,"passed_time":2.782908557,"remaining_time":19.12975725},
{"learn":[0.3446383681],"iteration":127,"passed_time":2.794995604,"remaining_time":19.04090755},
{"learn":[0.3446254031],"iteration":128,"passed_time":2.80498296,"remaining_time":18.93907099},
{"learn":[0.3446120879],"iteration":129,"passed_time":2.815132016,"remaining_time":18.83972965},
{"learn":[0.3445973438],"iteration":130,"passed_time":2.827827043,"remaining_time":18.75863893},
{"learn":[0.3445891769],"iteration":131,"passed_time":2.840031971,"remaining_time":18.67536175},
{"learn":[0.3445808203],"iteration":132,"passed_time":2.849855452,"remaining_time":18.57762915},
{"learn":[0.3445538633],"iteration":133,"passed_time":2.860060473,"remaining_time":18.4836744},
{"learn":[0.3445312682],"iteration":134,"passed_time":2.870094135,"remaining_time":18.38986242},
{"learn":[0.3445143531],"iteration":135,"passed_time":2.879904912,"remaining_time":18.2958665},
{"learn":[0.3444856382],"iteration":136,"passed_time":2.889883522,"remaining_time":18.20415678},
{"learn":[0.344474913],"iteration":137,"passed_time":2.899854057,"remaining_time":18.11358114},
{"learn":[0.3444691328],"iteration":138,"passed_time":2.909802129,"remaining_time":18.02402614},
{"learn":[0.3444650532],"iteration":139,"passed_time":2.919556512,"remaining_time":17.93441858},
{"learn":[0.3444575027],"iteration":140,"passed_time":2.932450469,"remaining_time":17.86507059},
{"learn":[0.3444537986],"iteration":141,"passed_time":2.943615953,"remaining_time":17.78607386},
{"learn":[0.3444351252],"iteration":142,"passed_time":2.953333819,"remaining_time":17.69935023},
{"learn":[0.3444234524],"iteration":143,"passed_time":2.9633345,"remaining_time":17.6153773},
{"learn":[0.3444178379],"iteration":144,"passed_time":2.973253408,"remaining_time":17.53194251},
{"learn":[0.3443983433],"iteration":145,"passed_time":2.98334065,"remaining_time":17.45049942},
{"learn":[0.3443851512],"iteration":146,"passed_time":2.993326092,"remaining_time":17.36943644},
{"learn":[0.3443581439],"iteration":147,"passed_time":3.003262594,"remaining_time":17.28905223},
{"learn":[0.3443457908],"iteration":148,"passed_time":3.013284724,"remaining_time":17.21010269},
{"learn":[0.344334308],"iteration":149,"passed_time":3.023135957,"remaining_time":17.13110376},
{"learn":[0.3443336552],"iteration":150,"passed_time":3.030445839,"remaining_time":17.0387319},
{"learn":[0.3443277639],"iteration":151,"passed_time":3.040439376,"remaining_time":16.96245126},
{"learn":[0.3443149364],"iteration":152,"passed_time":3.050553608,"remaining_time":16.88770527},
{"learn":[0.3443090369],"iteration":153,"passed_time":3.061451586,"remaining_time":16.81810417},
{"learn":[0.3442946424],"iteration":154,"passed_time":3.072650352,"remaining_time":16.75090031},
{"learn":[0.3442903037],"iteration":155,"passed_time":3.084263679,"remaining_time":16.68665734},
{"learn":[0.3442893252],"iteration":156,"passed_time":3.095287711,"remaining_time":16.61992064},
{"learn":[0.3442802411],"iteration":157,"passed_time":3.104611624,"remaining_time":16.54482903},
{"learn":[0.3442704739],"iteration":158,"passed_time":3.114822094,"remaining_time":16.47525397},
{"learn":[0.3442518573],"iteration":159,"passed_time":3.124533026,"remaining_time":16.40379839},
{"learn":[0.3442442846],"iteration":160,"passed_time":3.134086095,"remaining_time":16.33228717},
{"learn":[0.3442377716],"iteration":161,"passed_time":3.143922701,"remaining_time":16.26300755},
{"learn":[0.3442260147],"iteration":162,"passed_time":3.153822104,"remaining_time":16.19477976},
{"learn":[0.3441912123],"iteration":163,"passed_time":3.164006125,"remaining_time":16.12871415},
{"learn":[0.3441799386],"iteration":164,"passed_time":3.173538796,"remaining_time":16.06002967},
{"learn":[0.3441554986],"iteration":165,"passed_time":3.18413334,"remaining_time":15.99739281},
{"learn":[0.3441333216],"iteration":166,"passed_time":3.196930795,"remaining_time":15.94636738},
{"learn":[0.3441051368],"iteration":167,"passed_time":3.207237494,"remaining_time":15.88346188},
{"learn":[0.3440856508],"iteration":168,"passed_time":3.219599314,"remaining_time":15.8312842},
{"learn":[0.3440718227],"iteration":169,"passed_time":3.233345201,"remaining_time":15.78633245},
{"learn":[0.3440551285],"iteration":170,"passed_time":3.248939156,"remaining_time":15.75070503},
{"learn":[0.3440334059],"iteration":171,"passed_time":3.25936691,"remaining_time":15.69044071},
{"learn":[0.3440265693],"iteration":172,"passed_time":3.269238902,"remaining_time":15.62809579},
{"learn":[0.3439950141],"iteration":173,"passed_time":3.280889588,"remaining_time":15.5747977},
{"learn":[0.3439690862],"iteration":174,"passed_time":3.292616526,"remaining_time":15.52233505},
{"learn":[0.3439594075],"iteration":175,"passed_time":3.302398892,"remaining_time":15.46123117},
{"learn":[0.3439488866],"iteration":176,"passed_time":3.312522781,"remaining_time":15.40229519},
{"learn":[0.343913973],"iteration":177,"passed_time":3.323967304,"remaining_time":15.35000632},
{"learn":[0.3439041939],"iteration":178,"passed_time":3.33434731,"remaining_time":15.29329129},
{"learn":[0.3438962827],"iteration":179,"passed_time":3.345216795,"remaining_time":15.23932095},
{"learn":[0.3438808121],"iteration":180,"passed_time":3.355331978,"remaining_time":15.18241376},
{"learn":[0.3438639109],"iteration":181,"passed_time":3.365483879,"remaining_time":15.12618579},
{"learn":[0.3438502921],"iteration":182,"passed_time":3.375699129,"remaining_time":15.0707442},
{"learn":[0.3438279495],"iteration":183,"passed_time":3.385740805,"remaining_time":15.01502444},
{"learn":[0.3438146672],"iteration":184,"passed_time":3.395454413,"remaining_time":14.95835322},
{"learn":[0.3438014909],"iteration":185,"passed_time":3.40496897,"remaining_time":14.90131582},
{"learn":[0.3437603065],"iteration":186,"passed_time":3.415401543,"remaining_time":14.84877783},
{"learn":[0.3437434221],"iteration":187,"passed_time":3.425837122,"remaining_time":14.79670076},
{"learn":[0.3437169816],"iteration":188,"passed_time":3.436172294,"remaining_time":14.74463349},
{"learn":[0.343706412],"iteration":189,"passed_time":3.446363508,"remaining_time":14.6923918},
{"learn":[0.343691],"iteration":190,"passed_time":3.456491736,"remaining_time":14.64032364},
{"learn":[0.3436707212],"iteration":191,"passed_time":3.466248544,"remaining_time":14.58712929},
{"learn":[0.343652107],"iteration":192,"passed_time":3.476272277,"remaining_time":14.53550118},
{"learn":[0.3436164342],"iteration":193,"passed_time":3.486666529,"remaining_time":14.48584135},
{"learn":[0.3436025081],"iteration":194,"passed_time":3.496524044,"remaining_time":14.43436849},
{"learn":[0.343584417],"iteration":195,"passed_time":3.506617607,"remaining_time":14.38428855},
{"learn":[0.3435687642],"iteration":196,"passed_time":3.516704027,"remaining_time":14.33458545},
{"learn":[0.3435608098],"iteration":197,"passed_time":3.526217011,"remaining_time":14.28295981},
{"learn":[0.343540958],"iteration":198,"passed_time":3.53599082,"remaining_time":14.23280727},
{"learn":[0.3435218428],"iteration":199,"passed_time":3.546025224,"remaining_time":14.18410089},
{"learn":[0.3434928349],"iteration":200,"passed_time":3.55636289,"remaining_time":14.13698482},
{"learn":[0.3434899127],"iteration":201,"passed_time":3.567378046,"remaining_time":14.09290931},
{"learn":[0.3434775196],"iteration":202,"passed_time":3.576963265,"remaining_time":14.04354543},
{"learn":[0.3434527349],"iteration":203,"passed_time":3.590569003,"remaining_time":14.01025944},
{"learn":[0.3434357486],"iteration":204,"passed_time":3.600306495,"remaining_time":13.96216421},
{"learn":[0.3433932456],"iteration":205,"passed_time":3.610464688,"remaining_time":13.91606293},
{"learn":[0.3433917706],"iteration":206,"passed_time":3.619537886,"remaining_time":13.86615238},
{"learn":[0.3433646152],"iteration":207,"passed_time":3.629935264,"remaining_time":13.82167658},
{"learn":[0.3433611839],"iteration":208,"passed_time":3.639482101,"remaining_time":13.77430786},
{"learn":[0.3433324315],"iteration":209,"passed_time":3.649951292,"remaining_time":13.73076915},
{"learn":[0.3433245932],"iteration":210,"passed_time":3.659608254,"remaining_time":13.68450669},
{"learn":[0.3432961515],"iteration":211,"passed_time":3.66992956,"remaining_time":13.64105893},
{"learn":[0.3432691402],"iteration":212,"passed_time":3.680194562,"remaining_time":13.59771418},
{"learn":[0.3432428352],"iteration":213,"passed_time":3.690493637,"remaining_time":13.55480373},
{"learn":[0.3432194652],"iteration":214,"passed_time":3.700942962,"remaining_time":13.51274523},
{"learn":[0.3432054536],"iteration":215,"passed_time":3.712877515,"remaining_time":13.47637024},
{"learn":[0.343202152],"iteration":216,"passed_time":3.725368863,"remaining_time":13.44222959},
{"learn":[0.3431707377],"iteration":217,"passed_time":3.738507715,"remaining_time":13.41061024},
{"learn":[0.3431575147],"iteration":218,"passed_time":3.748854058,"remaining_time":13.369201},
{"learn":[0.3431280356],"iteration":219,"passed_time":3.759137463,"remaining_time":13.32785101},
{"learn":[0.3431102353],"iteration":220,"passed_time":3.770694005,"remaining_time":13.29126982},
{"learn":[0.3430751383],"iteration":221,"passed_time":3.780547613,"remaining_time":13.24894614},
{"learn":[0.3430441623],"iteration":222,"passed_time":3.792934496,"remaining_time":13.21574038},
{"learn":[0.3430150705],"iteration":223,"passed_time":3.802820945,"remaining_time":13.17405827},
{"learn":[0.3429850855],"iteration":224,"passed_time":3.814284533,"remaining_time":13.13809117},
{"learn":[0.3429660077],"iteration":225,"passed_time":3.825797143,"remaining_time":13.1025088},
{"learn":[0.3429426749],"iteration":226,"passed_time":3.836664264,"remaining_time":13.06494042},
{"learn":[0.3429231082],"iteration":227,"passed_time":3.846822247,"remaining_time":13.02520515},
{"learn":[0.3428925882],"iteration":228,"passed_time":3.855847836,"remaining_time":12.98191564},
{"learn":[0.3428775213],"iteration":229,"passed_time":3.865898099,"remaining_time":12.94235451},
{"learn":[0.3428645868],"iteration":230,"passed_time":3.87578599,"remaining_time":12.90250834},
{"learn":[0.3428625047],"iteration":231,"passed_time":3.88562455,"remaining_time":12.86275713},
{"learn":[0.3428328444],"iteration":232,"passed_time":3.896021607,"remaining_time":12.82510117},
{"learn":[0.3428097511],"iteration":233,"passed_time":3.905866859,"remaining_time":12.78587185},
{"learn":[0.3427759622],"iteration":234,"passed_time":3.918456519,"remaining_time":12.75582654},
{"learn":[0.3427465891],"iteration":235,"passed_time":3.931982099,"remaining_time":12.728959},
{"learn":[0.342723683],"iteration":236,"passed_time":3.942417838,"remaining_time":12.69225658},
{"learn":[0.3427115549],"iteration":237,"passed_time":3.952802883,"remaining_time":12.65561259},
{"learn":[0.3426992488],"iteration":238,"passed_time":3.962472027,"remaining_time":12.61690884},
{"learn":[0.3426818546],"iteration":239,"passed_time":3.972029605,"remaining_time":12.57809375},
{"learn":[0.3426658527],"iteration":240,"passed_time":3.982309063,"remaining_time":12.54179493},
{"learn":[0.3426574543],"iteration":241,"passed_time":3.992195802,"remaining_time":12.50448107},
{"learn":[0.3426469088],"iteration":242,"passed_time":4.002319551,"remaining_time":12.46813128},
{"learn":[0.342635381],"iteration":243,"passed_time":4.012574514,"remaining_time":12.432403},
{"learn":[0.342615596],"iteration":244,"passed_time":4.022514743,"remaining_time":12.39591278},
{"learn":[0.3425897857],"iteration":245,"passed_time":4.032493663,"remaining_time":12.359757},
{"learn":[0.3425778762],"iteration":246,"passed_time":4.042779964,"remaining_time":12.32475026},
{"learn":[0.3425482269],"iteration":247,"passed_time":4.05550675,"remaining_time":12.29734305},
{"learn":[0.3425178786],"iteration":248,"passed_time":4.068874827,"remaining_time":12.27198793},
{"learn":[0.3424979158],"iteration":249,"passed_time":4.079804794,"remaining_time":12.23941438},
{"learn":[0.3424785166],"iteration":250,"passed_time":4.089657791,"remaining_time":12.20379954},
{"learn":[0.3424493349],"iteration":251,"passed_time":4.100103107,"remaining_time":12.17014732},
{"learn":[0.3424316887],"iteration":252,"passed_time":4.110612914,"remaining_time":12.13686896},
{"learn":[0.3424145988],"iteration":253,"passed_time":4.12037397,"remaining_time":12.10157079},
{"learn":[0.3423896641],"iteration":254,"passed_time":4.130095962,"remaining_time":12.06635879},
{"learn":[0.3423763149],"iteration":255,"passed_time":4.14021887,"remaining_time":12.03251109},
{"learn":[0.3423622312],"iteration":256,"passed_time":4.150120777,"remaining_time":11.9982091},
{"learn":[0.3423282057],"iteration":257,"passed_time":4.160819515,"remaining_time":11.96638791},
{"learn":[0.3423164102],"iteration":258,"passed_time":4.171179052,"remaining_time":11.93375937},
{"learn":[0.3422939208],"iteration":259,"passed_time":4.185081322,"remaining_time":11.9113853},
{"learn":[0.3422806794],"iteration":260,"passed_time":4.207120367,"remaining_time":11.91211475},
{"learn":[0.3422676043],"iteration":261,"passed_time":4.229457949,"remaining_time":11.91351132},
{"learn":[0.3422456176],"iteration":262,"passed_time":4.243990622,"remaining_time":11.89285585},
{"learn":[0.3422446813],"iteration":263,"passed_time":4.252670398,"remaining_time":11.85592959},
{"learn":[0.3422184504],"iteration":264,"passed_time":4.264317157,"remaining_time":11.8274457},
{"learn":[0.3421951628],"iteration":265,"passed_time":4.27784416,"remaining_time":11.80427674},
{"learn":[0.3421660596],"iteration":266,"passed_time":4.287969853,"remaining_time":11.77184233},
{"learn":[0.3421495309],"iteration":267,"passed_time":4.298182828,"remaining_time":11.7398128},
{"learn":[0.342124423],"iteration":268,"passed_time":4.310426465,"remaining_time":11.71346374},
{"learn":[0.3421118389],"iteration":269,"passed_time":4.320513577,"remaining_time":11.68138856},
{"learn":[0.3420907558],"iteration":270,"passed_time":4.330440901,"remaining_time":11.64904582},
{"learn":[0.3420691665],"iteration":271,"passed_time":4.341865367,"remaining_time":11.62087495},
{"learn":[0.3420316323],"iteration":272,"passed_time":4.357892925,"remaining_time":11.60508482},
{"learn":[0.3420150524],"iteration":273,"passed_time":4.368012477,"remaining_time":11.5736389},
{"learn":[0.3419994906],"iteration":274,"passed_time":4.378066908,"remaining_time":11.54217639},
{"learn":[0.341981436],"iteration":275,"passed_time":4.38769706,"remaining_time":11.50975606},
{"learn":[0.3419720524],"iteration":276,"passed_time":4.401533114,"remaining_time":11.48847813},
{"learn":[0.3419476748],"iteration":277,"passed_time":4.429129476,"remaining_time":11.50299094},
{"learn":[0.3419453948],"iteration":278,"passed_time":4.455765885,"remaining_time":11.51472116},
{"learn":[0.3419287443],"iteration":279,"passed_time":4.470518517,"remaining_time":11.49561904},
{"learn":[0.3419174053],"iteration":280,"passed_time":4.480222757,"remaining_time":11.46363047},
{"learn":[0.3419150279],"iteration":281,"passed_time":4.490207789,"remaining_time":11.43251487},
{"learn":[0.3418953695],"iteration":282,"passed_time":4.500306692,"remaining_time":11.4018371},
{"learn":[0.3418752531],"iteration":283,"passed_time":4.510390607,"remaining_time":11.37126646},
{"learn":[0.3418531705],"iteration":284,"passed_time":4.520659466,"remaining_time":11.34130357},
{"learn":[0.3418338361],"iteration":285,"passed_time":4.533053834,"remaining_time":11.31678475},
{"learn":[0.3418190025],"iteration":286,"passed_time":4.543282739,"remaining_time":11.28697071},
{"learn":[0.3417979255],"iteration":287,"passed_time":4.556072141,"remaining_time":11.26362279},
{"learn":[0.3417675731],"iteration":288,"passed_time":4.566757785,"remaining_time":11.23517227},
{"learn":[0.3417524761],"iteration":289,"passed_time":4.576716377,"remaining_time":11.20506423},
{"learn":[0.3417365424],"iteration":290,"passed_time":4.586763985,"remaining_time":11.17531156},
{"learn":[0.3417222891],"iteration":291,"passed_time":4.59744542,"remaining_time":11.14723068},
{"learn":[0.3417019562],"iteration":292,"passed_time":4.60710105,"remaining_time":11.11679332},
{"learn":[0.3417000137],"iteration":293,"passed_time":4.617056797,"remaining_time":11.08721802},
{"learn":[0.341679485],"iteration":294,"passed_time":4.627079668,"remaining_time":11.05793616},
{"learn":[0.3416557033],"iteration":295,"passed_time":4.637343809,"remaining_time":11.02935825},
{"learn":[0.3416331871],"iteration":296,"passed_time":4.647416032,"remaining_time":11.0004494},
{"learn":[0.341621207],"iteration":297,"passed_time":4.65735603,"remaining_time":10.97135548},
{"learn":[0.3416116118],"iteration":298,"passed_time":4.667316807,"remaining_time":10.9424384},
{"learn":[0.3415948332],"iteration":299,"passed_time":4.67757197,"remaining_time":10.9143346},
{"learn":[0.3415771393],"iteration":300,"passed_time":4.687860977,"remaining_time":10.88642798},
{"learn":[0.3415521001],"iteration":301,"passed_time":4.702718028,"remaining_time":10.86919597},
{"learn":[0.3415372945],"iteration":302,"passed_time":4.715682765,"remaining_time":10.84762669},
{"learn":[0.3415143842],"iteration":303,"passed_time":4.72639592,"remaining_time":10.82095908},
{"learn":[0.3414963669],"iteration":304,"passed_time":4.736668155,"remaining_time":10.79339137},
{"learn":[0.3414788528],"iteration":305,"passed_time":4.747001524,"remaining_time":10.76607535},
{"learn":[0.341463231],"iteration":306,"passed_time":4.758319883,"remaining_time":10.74109342},
{"learn":[0.3414308923],"iteration":307,"passed_time":4.769581196,"remaining_time":10.71607204},
{"learn":[0.3413988013],"iteration":308,"passed_time":4.779996437,"remaining_time":10.6892477},
{"learn":[0.3413788368],"iteration":309,"passed_time":4.790056898,"remaining_time":10.66173955},
{"learn":[0.3413614389],"iteration":310,"passed_time":4.802467066,"remaining_time":10.63954922},
{"learn":[0.3413492994],"iteration":311,"passed_time":4.813909035,"remaining_time":10.61528659},
{"learn":[0.3413371279],"iteration":312,"passed_time":4.824093918,"remaining_time":10.58834671},
{"learn":[0.3413244663],"iteration":313,"passed_time":4.83427874,"remaining_time":10.56151343},
{"learn":[0.3413204481],"iteration":314,"passed_time":4.844175628,"remaining_time":10.5341597},
{"learn":[0.341318733],"iteration":315,"passed_time":4.854098645,"remaining_time":10.50697302},
{"learn":[0.341301766],"iteration":316,"passed_time":4.864237382,"remaining_time":10.48036004},
{"learn":[0.3412836992],"iteration":317,"passed_time":4.87454893,"remaining_time":10.45422129},
{"learn":[0.3412630652],"iteration":318,"passed_time":4.884498185,"remaining_time":10.42740835},
{"learn":[0.3412434808],"iteration":319,"passed_time":4.894553877,"remaining_time":10.40092699},
{"learn":[0.3412238757],"iteration":320,"passed_time":4.908766243,"remaining_time":10.38334043},
{"learn":[0.3411981599],"iteration":321,"passed_time":4.921305072,"remaining_time":10.36225105},
{"learn":[0.3411940476],"iteration":322,"passed_time":4.930682014,"remaining_time":10.33458738},
{"learn":[0.3411733983],"iteration":323,"passed_time":4.940816042,"remaining_time":10.30861619},
{"learn":[0.3411656278],"iteration":324,"passed_time":4.950870874,"remaining_time":10.28257797},
{"learn":[0.3411644518],"iteration":325,"passed_time":4.960832392,"remaining_time":10.25644488},
{"learn":[0.3411464263],"iteration":326,"passed_time":4.970721636,"remaining_time":10.23026196},
{"learn":[0.3411212416],"iteration":327,"passed_time":4.980959627,"remaining_time":10.20489289},
{"learn":[0.3411025284],"iteration":328,"passed_time":4.991057859,"remaining_time":10.17933077},
{"learn":[0.3410874085],"iteration":329,"passed_time":5.001029786,"remaining_time":10.15360593},
{"learn":[0.3410711603],"iteration":330,"passed_time":5.010992606,"remaining_time":10.12795787},
{"learn":[0.3410497066],"iteration":331,"passed_time":5.021130411,"remaining_time":10.10275637},
{"learn":[0.3410293618],"iteration":332,"passed_time":5.033311563,"remaining_time":10.08173818},
{"learn":[0.3410142838],"iteration":333,"passed_time":5.043308166,"remaining_time":10.05641688},
{"learn":[0.3409853417],"iteration":334,"passed_time":5.055347505,"remaining_time":10.03524206},
{"learn":[0.3409683104],"iteration":335,"passed_time":5.067346628,"remaining_time":10.01404215},
{"learn":[0.340947217],"iteration":336,"passed_time":5.077433549,"remaining_time":9.989134846},
{"learn":[0.3409376543],"iteration":337,"passed_time":5.087177934,"remaining_time":9.963644355},
{"learn":[0.3409292232],"iteration":338,"passed_time":5.09711155,"remaining_time":9.938615735},
{"learn":[0.34091352],"iteration":339,"passed_time":5.106689815,"remaining_time":9.912986112},
{"learn":[0.3408973911],"iteration":340,"passed_time":5.116882553,"remaining_time":9.88863813},
{"learn":[0.3408809007],"iteration":341,"passed_time":5.126777477,"remaining_time":9.863799941},
{"learn":[0.3408562244],"iteration":342,"passed_time":5.137437372,"remaining_time":9.84051415},
{"learn":[0.3408505729],"iteration":343,"passed_time":5.147138316,"remaining_time":9.815473068},
{"learn":[0.3408408935],"iteration":344,"passed_time":5.157107829,"remaining_time":9.791030805},
{"learn":[0.3408270003],"iteration":345,"passed_time":5.16718408,"remaining_time":9.766873954},
{"learn":[0.3408143139],"iteration":346,"passed_time":5.178008852,"remaining_time":9.744206859},
{"learn":[0.3408073823],"iteration":347,"passed_time":5.195099836,"remaining_time":9.733347968},
{"learn":[0.3407864913],"iteration":348,"passed_time":5.207019722,"remaining_time":9.712807562},
{"learn":[0.3407778892],"iteration":349,"passed_time":5.218892461,"remaining_time":9.692228857},
{"learn":[0.3407762689],"iteration":350,"passed_time":5.228566976,"remaining_time":9.667635235},
{"learn":[0.3407667686],"iteration":351,"passed_time":5.238344522,"remaining_time":9.643316052},
{"learn":[0.3407453078],"iteration":352,"passed_time":5.249786,"remaining_time":9.622129013},
{"learn":[0.340728464],"iteration":353,"passed_time":5.259679281,"remaining_time":9.598171795},
{"learn":[0.3407167073],"iteration":354,"passed_time":5.270635617,"remaining_time":9.576225276},
{"learn":[0.3406982871],"iteration":355,"passed_time":5.2807827,"remaining_time":9.552876569},
{"learn":[0.3406814694],"iteration":356,"passed_time":5.29183833,"remaining_time":9.531238225},
{"learn":[0.3406670548],"iteration":357,"passed_time":5.305068922,"remaining_time":9.513559352},
{"learn":[0.3406532764],"iteration":358,"passed_time":5.315734979,"remaining_time":9.491326244},
{"learn":[0.3406436504],"iteration":359,"passed_time":5.325626748,"remaining_time":9.467780885},
{"learn":[0.3406323744],"iteration":360,"passed_time":5.335857856,"remaining_time":9.444911829},
{"learn":[0.3406168536],"iteration":361,"passed_time":5.345896838,"remaining_time":9.421773985},
{"learn":[0.3405868726],"iteration":362,"passed_time":5.35617291,"remaining_time":9.399124364},
{"learn":[0.3405641239],"iteration":363,"passed_time":5.366182327,"remaining_time":9.376076814},
{"learn":[0.3405449323],"iteration":364,"passed_time":5.376542115,"remaining_time":9.353710255},
{"learn":[0.3405339205],"iteration":365,"passed_time":5.386439394,"remaining_time":9.330608131},
{"learn":[0.3405263036],"iteration":366,"passed_time":5.396657488,"remaining_time":9.308131308},
{"learn":[0.3405172146],"iteration":367,"passed_time":5.406527476,"remaining_time":9.285123274},
{"learn":[0.3405157392],"iteration":368,"passed_time":5.416278162,"remaining_time":9.26198244},
{"learn":[0.3405045786],"iteration":369,"passed_time":5.427115878,"remaining_time":9.240764874},
{"learn":[0.3404877384],"iteration":370,"passed_time":5.437343761,"remaining_time":9.218569342},
{"learn":[0.3404687296],"iteration":371,"passed_time":5.447473321,"remaining_time":9.196272166},
{"learn":[0.3404604765],"iteration":372,"passed_time":5.457380348,"remaining_time":9.173666161},
{"learn":[0.340445589],"iteration":373,"passed_time":5.467501653,"remaining_time":9.151486724},
{"learn":[0.3404289289],"iteration":374,"passed_time":5.47739833,"remaining_time":9.128997217},
{"learn":[0.3404035557],"iteration":375,"passed_time":5.487453191,"remaining_time":9.106837211},
{"learn":[0.3404019234],"iteration":376,"passed_time":5.496856041,"remaining_time":9.083663962},
{"learn":[0.340396666],"iteration":377,"passed_time":5.506881288,"remaining_time":9.061587727},
{"learn":[0.3403827221],"iteration":378,"passed_time":5.518856517,"remaining_time":9.042770177},
{"learn":[0.3403549017],"iteration":379,"passed_time":5.529028055,"remaining_time":9.021045774},
{"learn":[0.3403439973],"iteration":380,"passed_time":5.542324229,"remaining_time":9.004458524},
{"learn":[0.3403329742],"iteration":381,"passed_time":5.55240061,"remaining_time":8.982679521},
{"learn":[0.3403119188],"iteration":382,"passed_time":5.562807145,"remaining_time":8.961493494},
{"learn":[0.3402936599],"iteration":383,"passed_time":5.573276026,"remaining_time":8.940463624},
{"learn":[0.340277273],"iteration":384,"passed_time":5.583831326,"remaining_time":8.919626664},
{"learn":[0.3402690307],"iteration":385,"passed_time":5.5934565,"remaining_time":8.897363448},
{"learn":[0.3402539915],"iteration":386,"passed_time":5.60362364,"remaining_time":8.876024008},
{"learn":[0.3402297233],"iteration":387,"passed_time":5.61406034,"remaining_time":8.855167341},
{"learn":[0.3402072511],"iteration":388,"passed_time":5.624036405,"remaining_time":8.833640729},
{"learn":[0.3402021292],"iteration":389,"passed_time":5.634030063,"remaining_time":8.812200867},
{"learn":[0.3401728157],"iteration":390,"passed_time":5.644441466,"remaining_time":8.791470212},
{"learn":[0.3401590552],"iteration":391,"passed_time":5.654194908,"remaining_time":8.769771694},
{"learn":[0.3401526747],"iteration":392,"passed_time":5.664071217,"remaining_time":8.748323738},
{"learn":[0.3401389414],"iteration":393,"passed_time":5.674922087,"remaining_time":8.728433464},
{"learn":[0.3401260186],"iteration":394,"passed_time":5.689157606,"remaining_time":8.713773042},
{"learn":[0.3401109971],"iteration":395,"passed_time":5.700663553,"remaining_time":8.694951481},
{"learn":[0.3400942404],"iteration":396,"passed_time":5.711416412,"remaining_time":8.675022912},
{"learn":[0.3400801227],"iteration":397,"passed_time":5.720978427,"remaining_time":8.653339229},
{"learn":[0.3400644632],"iteration":398,"passed_time":5.731081738,"remaining_time":8.632531641},
{"learn":[0.3400471802],"iteration":399,"passed_time":5.742595861,"remaining_time":8.613893792},
{"learn":[0.3400314923],"iteration":400,"passed_time":5.754352935,"remaining_time":8.595654385},
{"learn":[0.3400194743],"iteration":401,"passed_time":5.764250204,"remaining_time":8.574680652},
{"learn":[0.3400061785],"iteration":402,"passed_time":5.775352972,"remaining_time":8.555547703},
{"learn":[0.3399884404],"iteration":403,"passed_time":5.785742576,"remaining_time":8.535402413},
{"learn":[0.3399822933],"iteration":404,"passed_time":5.797298333,"remaining_time":8.517018539},
{"learn":[0.3399650415],"iteration":405,"passed_time":5.807552845,"remaining_time":8.496764508},
{"learn":[0.3399582284],"iteration":406,"passed_time":5.817687024,"remaining_time":8.476384289},
{"learn":[0.3399427928],"iteration":407,"passed_time":5.827502461,"remaining_time":8.455591806},
{"learn":[0.3399219541],"iteration":408,"passed_time":5.837202453,"remaining_time":8.434686185},
{"learn":[0.3399131324],"iteration":409,"passed_time":5.846917813,"remaining_time":8.413857341},
{"learn":[0.3399011765],"iteration":410,"passed_time":5.856916751,"remaining_time":8.393488969},
{"learn":[0.3398733637],"iteration":411,"passed_time":5.866877868,"remaining_time":8.373116957},
{"learn":[0.3398599929],"iteration":412,"passed_time":5.876753125,"remaining_time":8.352673328},
{"learn":[0.3398560975],"iteration":413,"passed_time":5.894362272,"remaining_time":8.343227756},
{"learn":[0.3398430122],"iteration":414,"passed_time":5.904490198,"remaining_time":8.323197027},
{"learn":[0.339825869],"iteration":415,"passed_time":5.914412974,"remaining_time":8.302925906},
{"learn":[0.339797233],"iteration":416,"passed_time":5.924812085,"remaining_time":8.283370374},
{"learn":[0.3397800542],"iteration":417,"passed_time":5.935363529,"remaining_time":8.264070752},
{"learn":[0.3397475722],"iteration":418,"passed_time":5.94560075,"remaining_time":8.244377173},
{"learn":[0.3397295658],"iteration":419,"passed_time":5.955597062,"remaining_time":8.224395943},
{"learn":[0.3397139689],"iteration":420,"passed_time":5.965519818,"remaining_time":8.204360985},
{"learn":[0.3396999222],"iteration":421,"passed_time":5.97541868,"remaining_time":8.184341225},
{"learn":[0.3396820763],"iteration":422,"passed_time":5.985527702,"remaining_time":8.16465599},
{"learn":[0.3396690507],"iteration":423,"passed_time":5.995441922,"remaining_time":8.14475129},
{"learn":[0.3396602795],"iteration":424,"passed_time":6.007574275,"remaining_time":8.127894608},
{"learn":[0.3396459386],"iteration":425,"passed_time":6.017434675,"remaining_time":8.107998835},
{"learn":[0.3396288957],"iteration":426,"passed_time":6.029900075,"remaining_time":8.091645768},
{"learn":[0.3396026198],"iteration":427,"passed_time":6.04023653,"remaining_time":8.072465643},
{"learn":[0.3395761894],"iteration":428,"passed_time":6.050545864,"remaining_time":8.053290649},
{"learn":[0.3395616735],"iteration":429,"passed_time":6.060479921,"remaining_time":8.03365943},
{"learn":[0.339544427],"iteration":430,"passed_time":6.070876487,"remaining_time":8.014683808},
{"learn":[0.3395318848],"iteration":431,"passed_time":6.081343855,"remaining_time":7.995840994},
{"learn":[0.3395307326],"iteration":432,"passed_time":6.091453698,"remaining_time":7.9765687},
{"learn":[0.3395124543],"iteration":433,"passed_time":6.102134823,"remaining_time":7.958083663},
{"learn":[0.3395006879],"iteration":434,"passed_time":6.111908763,"remaining_time":7.938456209},
{"learn":[0.3394901001],"iteration":435,"passed_time":6.121908752,"remaining_time":7.919166367},
{"learn":[0.339473569],"iteration":436,"passed_time":6.132230008,"remaining_time":7.900332939},
{"learn":[0.3394642912],"iteration":437,"passed_time":6.142350482,"remaining_time":7.881280755},
{"learn":[0.3394389909],"iteration":438,"passed_time":6.15300127,"remaining_time":7.862946953},
{"learn":[0.3394240408],"iteration":439,"passed_time":6.163038819,"remaining_time":7.843867588},
{"learn":[0.3394115981],"iteration":440,"passed_time":6.177906282,"remaining_time":7.8309515},
{"learn":[0.3394059588],"iteration":441,"passed_time":6.187755912,"remaining_time":7.811691853},
{"learn":[0.3393919745],"iteration":442,"passed_time":6.201042748,"remaining_time":7.796796412},
{"learn":[0.3393748192],"iteration":443,"passed_time":6.211484528,"remaining_time":7.77834549},
{"learn":[0.3393540949],"iteration":444,"passed_time":6.22216962,"remaining_time":7.760234021},
{"learn":[0.3393266209],"iteration":445,"passed_time":6.233549664,"remaining_time":7.743019089},
{"learn":[0.3393166047],"iteration":446,"passed_time":6.243552829,"remaining_time":7.724126878},
{"learn":[0.3393061222],"iteration":447,"passed_time":6.254574367,"remaining_time":7.70652913},
{"learn":[0.3392956619],"iteration":448,"passed_time":6.264401605,"remaining_time":7.687495065},
{"learn":[0.3392840801],"iteration":449,"passed_time":6.277175378,"remaining_time":7.67210324},
{"learn":[0.339283001],"iteration":450,"passed_time":6.288755203,"remaining_time":7.655269637},
{"learn":[0.3392725317],"iteration":451,"passed_time":6.299514313,"remaining_time":7.637464255},
{"learn":[0.339260337],"iteration":452,"passed_time":6.309643853,"remaining_time":7.618929773},
{"learn":[0.3392559955],"iteration":453,"passed_time":6.319351319,"remaining_time":7.599924714},
{"learn":[0.3392423482],"iteration":454,"passed_time":6.329256181,"remaining_time":7.581196965},
{"learn":[0.3392300767],"iteration":455,"passed_time":6.339239039,"remaining_time":7.562600959},
{"learn":[0.3392294426],"iteration":456,"passed_time":6.348708022,"remaining_time":7.54343207},
{"learn":[0.3392169524],"iteration":457,"passed_time":6.358755971,"remaining_time":7.52499069},
{"learn":[0.3392009786],"iteration":458,"passed_time":6.369147598,"remaining_time":7.506990959},
{"learn":[0.3391889728],"iteration":459,"passed_time":6.378989353,"remaining_time":7.488378806},
{"learn":[0.3391779834],"iteration":460,"passed_time":6.388861595,"remaining_time":7.469840347},
{"learn":[0.3391614233],"iteration":461,"passed_time":6.405267436,"remaining_time":7.458947794},
{"learn":[0.3391291372],"iteration":462,"passed_time":6.435511075,"remaining_time":7.46408088},
{"learn":[0.3391081986],"iteration":463,"passed_time":6.467053269,"remaining_time":7.470561535},
{"learn":[0.3390841786],"iteration":464,"passed_time":6.50590344,"remaining_time":7.485286754},
{"learn":[0.3390679659],"iteration":465,"passed_time":6.533032024,"remaining_time":7.486350001},
{"learn":[0.339055416],"iteration":466,"passed_time":6.545473369,"remaining_time":7.470529563},
{"learn":[0.3390419434],"iteration":467,"passed_time":6.557861994,"remaining_time":7.454663635},
{"learn":[0.3390195915],"iteration":468,"passed_time":6.568235638,"remaining_time":7.436531181},
{"learn":[0.3390058185],"iteration":469,"passed_time":6.578176177,"remaining_time":7.417943348},
{"learn":[0.3389945018],"iteration":470,"passed_time":6.588200852,"remaining_time":7.399486732},
{"learn":[0.338975899],"iteration":471,"passed_time":6.598321055,"remaining_time":7.381172705},
{"learn":[0.33895551],"iteration":472,"passed_time":6.60864197,"remaining_time":7.363116952},
{"learn":[0.3389393725],"iteration":473,"passed_time":6.618623245,"remaining_time":7.344716935},
{"learn":[0.3389111327],"iteration":474,"passed_time":6.628781749,"remaining_time":7.326548249},
{"learn":[0.3388956267],"iteration":475,"passed_time":6.639252353,"remaining_time":7.308756792},
{"learn":[0.3388601059],"iteration":476,"passed_time":6.649537071,"remaining_time":7.290792219},
{"learn":[0.3388420105],"iteration":477,"passed_time":6.665163136,"remaining_time":7.278692797},
{"learn":[0.3388272885],"iteration":478,"passed_time":6.675737663,"remaining_time":7.26108418},
{"learn":[0.3388042528],"iteration":479,"passed_time":6.694344433,"remaining_time":7.252206469},
{"learn":[0.3387929128],"iteration":480,"passed_time":6.704322021,"remaining_time":7.233977399},
{"learn":[0.3387702585],"iteration":481,"passed_time":6.716583813,"remaining_time":7.218237376},
{"learn":[0.3387596966],"iteration":482,"passed_time":6.727146778,"remaining_time":7.200693343},
{"learn":[0.3387420191],"iteration":483,"passed_time":6.739088593,"remaining_time":7.18464817},
{"learn":[0.3387232434],"iteration":484,"passed_time":6.74915181,"remaining_time":7.166625118},
{"learn":[0.3387105354],"iteration":485,"passed_time":6.759736656,"remaining_time":7.149186505},
{"learn":[0.3386856006],"iteration":486,"passed_time":6.770458206,"remaining_time":7.13192004},
{"learn":[0.338656689],"iteration":487,"passed_time":6.782164476,"remaining_time":7.115713548},
{"learn":[0.3386490471],"iteration":488,"passed_time":6.79349681,"remaining_time":7.099134704},
{"learn":[0.3386313196],"iteration":489,"passed_time":6.803622323,"remaining_time":7.081321193},
{"learn":[0.3386196343],"iteration":490,"passed_time":6.813561599,"remaining_time":7.063345935},
{"learn":[0.3386142603],"iteration":491,"passed_time":6.823311494,"remaining_time":7.045207803},
{"learn":[0.3385955838],"iteration":492,"passed_time":6.833475007,"remaining_time":7.027529064},
{"learn":[0.3385774441],"iteration":493,"passed_time":6.843865863,"remaining_time":7.010113617},
{"learn":[0.3385599425],"iteration":494,"passed_time":6.853893784,"remaining_time":6.992356285},
{"learn":[0.3385507298],"iteration":495,"passed_time":6.868328786,"remaining_time":6.979108282},
{"learn":[0.3385403948],"iteration":496,"passed_time":6.879835212,"remaining_time":6.962891573},
{"learn":[0.3385228762],"iteration":497,"passed_time":6.890280288,"remaining_time":6.945623905},
{"learn":[0.3384834656],"iteration":498,"passed_time":6.900649974,"remaining_time":6.92830789},
{"learn":[0.3384749789],"iteration":499,"passed_time":6.910880041,"remaining_time":6.910880041},
{"learn":[0.3384565429],"iteration":500,"passed_time":6.921105489,"remaining_time":6.893476326},
{"learn":[0.3384360577],"iteration":501,"passed_time":6.931139632,"remaining_time":6.875911428},
{"learn":[0.3384321823],"iteration":502,"passed_time":6.940885399,"remaining_time":6.858091538},
{"learn":[0.3384167266],"iteration":503,"passed_time":6.950874168,"remaining_time":6.840542832},
{"learn":[0.3384024224],"iteration":504,"passed_time":6.961214029,"remaining_time":6.823368206},
{"learn":[0.3383854266],"iteration":505,"passed_time":6.971829471,"remaining_time":6.806489642},
{"learn":[0.338360279],"iteration":506,"passed_time":6.981814974,"remaining_time":6.789023239},
{"learn":[0.3383397728],"iteration":507,"passed_time":6.992195581,"remaining_time":6.771968948},
{"learn":[0.3383288948],"iteration":508,"passed_time":7.005133459,"remaining_time":6.757407717},
{"learn":[0.3383169204],"iteration":509,"passed_time":7.015164476,"remaining_time":6.740059986},
{"learn":[0.3383052624],"iteration":510,"passed_time":7.029682101,"remaining_time":6.727034339},
{"learn":[0.3382991258],"iteration":511,"passed_time":7.039441974,"remaining_time":6.709468131},
{"learn":[0.3382864145],"iteration":512,"passed_time":7.049312914,"remaining_time":6.692037795},
{"learn":[0.3382618821],"iteration":513,"passed_time":7.059694372,"remaining_time":6.675119581},
{"learn":[0.3382479945],"iteration":514,"passed_time":7.070447861,"remaining_time":6.658577112},
{"learn":[0.3382188307],"iteration":515,"passed_time":7.080674491,"remaining_time":6.641562895},
{"learn":[0.338187517],"iteration":516,"passed_time":7.091171344,"remaining_time":6.624827387},
{"learn":[0.3381760686],"iteration":517,"passed_time":7.101123765,"remaining_time":6.607609372},
{"learn":[0.3381631109],"iteration":518,"passed_time":7.111241694,"remaining_time":6.590572745},
{"learn":[0.3381490981],"iteration":519,"passed_time":7.122116809,"remaining_time":6.57426167},
{"learn":[0.3381433153],"iteration":520,"passed_time":7.131886551,"remaining_time":6.556955198},
{"learn":[0.338122945],"iteration":521,"passed_time":7.142647825,"remaining_time":6.540585556},
{"learn":[0.3381084532],"iteration":522,"passed_time":7.155800852,"remaining_time":6.52641875},
{"learn":[0.3380941426],"iteration":523,"passed_time":7.168627844,"remaining_time":6.511959645},
{"learn":[0.3380762704],"iteration":524,"passed_time":7.181521891,"remaining_time":6.497567425},
{"learn":[0.3380678985],"iteration":525,"passed_time":7.191400735,"remaining_time":6.48046378},
{"learn":[0.3380491164],"iteration":526,"passed_time":7.20160823,"remaining_time":6.463682529},
{"learn":[0.3380343725],"iteration":527,"passed_time":7.213603134,"remaining_time":6.448524013},
{"learn":[0.3380247543],"iteration":528,"passed_time":7.223203731,"remaining_time":6.431245666},
{"learn":[0.3380131128],"iteration":529,"passed_time":7.234442873,"remaining_time":6.41544934},
{"learn":[0.3379883366],"iteration":530,"passed_time":7.244776241,"remaining_time":6.398870164},
{"learn":[0.3379761796],"iteration":531,"passed_time":7.256224802,"remaining_time":6.383295503},
{"learn":[0.3379637456],"iteration":532,"passed_time":7.266213981,"remaining_time":6.366457654},
{"learn":[0.3379389718],"iteration":533,"passed_time":7.279055162,"remaining_time":6.35213428},
{"learn":[0.3379313503],"iteration":534,"passed_time":7.288942843,"remaining_time":6.335249387},
{"learn":[0.3379281576],"iteration":535,"passed_time":7.298165959,"remaining_time":6.317815308},
{"learn":[0.3379114418],"iteration":536,"passed_time":7.308466918,"remaining_time":6.301341123},
{"learn":[0.3378974787],"iteration":537,"passed_time":7.319242137,"remaining_time":6.285297151},
{"learn":[0.3378854504],"iteration":538,"passed_time":7.329212983,"remaining_time":6.268584759},
{"learn":[0.337878021],"iteration":539,"passed_time":7.339054267,"remaining_time":6.251786968},
{"learn":[0.3378641352],"iteration":540,"passed_time":7.348916761,"remaining_time":6.23503289},
{"learn":[0.3378584025],"iteration":541,"passed_time":7.359063724,"remaining_time":6.218544622},
{"learn":[0.3378404553],"iteration":542,"passed_time":7.369723659,"remaining_time":6.202511441},
{"learn":[0.3378297201],"iteration":543,"passed_time":7.379846347,"remaining_time":6.186047673},
{"learn":[0.3378068962],"iteration":544,"passed_time":7.390185536,"remaining_time":6.169787925},
{"learn":[0.3377958188],"iteration":545,"passed_time":7.400136705,"remaining_time":6.153227224},
{"learn":[0.3377825045],"iteration":546,"passed_time":7.410091611,"remaining_time":6.136693784},
{"learn":[0.3377746232],"iteration":547,"passed_time":7.420400314,"remaining_time":6.120476171},
{"learn":[0.3377737715],"iteration":548,"passed_time":7.430055773,"remaining_time":6.103743449},
{"learn":[0.3377698347],"iteration":549,"passed_time":7.440192046,"remaining_time":6.087429856},
{"learn":[0.3377672688],"iteration":550,"passed_time":7.450249943,"remaining_time":6.071074817},
{"learn":[0.3377415406],"iteration":551,"passed_time":7.460721599,"remaining_time":6.055078399},
{"learn":[0.3377306961],"iteration":552,"passed_time":7.470698475,"remaining_time":6.038702022},
{"learn":[0.3377135449],"iteration":553,"passed_time":7.480914907,"remaining_time":6.022541603},
{"learn":[0.3377017465],"iteration":554,"passed_time":7.49347339,"remaining_time":6.008280466},
{"learn":[0.3376909279],"iteration":555,"passed_time":7.503248361,"remaining_time":5.991802648},
{"learn":[0.3376768926],"iteration":556,"passed_time":7.517755883,"remaining_time":5.979112848},
{"learn":[0.3376448991],"iteration":557,"passed_time":7.528455823,"remaining_time":5.963400491},
{"learn":[0.3376321625],"iteration":558,"passed_time":7.538644453,"remaining_time":5.94730269},
{"learn":[0.3376222538],"iteration":559,"passed_time":7.548554716,"remaining_time":5.931007277},
{"learn":[0.3376065838],"iteration":560,"passed_time":7.558726684,"remaining_time":5.91493942},
{"learn":[0.3375901723],"iteration":561,"passed_time":7.569569139,"remaining_time":5.899415094},
{"learn":[0.3375755084],"iteration":562,"passed_time":7.579750034,"remaining_time":5.883393899},
{"learn":[0.3375685517],"iteration":563,"passed_time":7.589700422,"remaining_time":5.86721522},
{"learn":[0.3375578142],"iteration":564,"passed_time":7.599729114,"remaining_time":5.851118876},
{"learn":[0.3375498517],"iteration":565,"passed_time":7.609628246,"remaining_time":5.834944627},
{"learn":[0.3375496945],"iteration":566,"passed_time":7.61891453,"remaining_time":5.8183245},
{"learn":[0.3375313312],"iteration":567,"passed_time":7.628870387,"remaining_time":5.802239449},
{"learn":[0.3375189317],"iteration":568,"passed_time":7.639011599,"remaining_time":5.786316343},
{"learn":[0.3375055703],"iteration":569,"passed_time":7.65648855,"remaining_time":5.775947503},
{"learn":[0.3374952952],"iteration":570,"passed_time":7.670382735,"remaining_time":5.762861985},
{"learn":[0.3374733822],"iteration":571,"passed_time":7.700049326,"remaining_time":5.76157537},
{"learn":[0.337456557],"iteration":572,"passed_time":7.726869104,"remaining_time":5.75806825},
{"learn":[0.3374470678],"iteration":573,"passed_time":7.739579459,"remaining_time":5.744008448},
{"learn":[0.3374390434],"iteration":574,"passed_time":7.751971124,"remaining_time":5.729717787},
{"learn":[0.3374321308],"iteration":575,"passed_time":7.762810062,"remaining_time":5.71429074},
{"learn":[0.3374130864],"iteration":576,"passed_time":7.774114615,"remaining_time":5.69922094},
{"learn":[0.3374036619],"iteration":577,"passed_time":7.784187109,"remaining_time":5.683264637},
{"learn":[0.3373939301],"iteration":578,"passed_time":7.794040637,"remaining_time":5.667169444},
{"learn":[0.3373877864],"iteration":579,"passed_time":7.804227884,"remaining_time":5.651337433},
{"learn":[0.337378055],"iteration":580,"passed_time":7.814196856,"remaining_time":5.63536744},
{"learn":[0.3373756916],"iteration":581,"passed_time":7.823981575,"remaining_time":5.619285736},
{"learn":[0.337361991],"iteration":582,"passed_time":7.833841595,"remaining_time":5.603279494},
{"learn":[0.3373497974],"iteration":583,"passed_time":7.844091729,"remaining_time":5.58757219},
{"learn":[0.3373337966],"iteration":584,"passed_time":7.857567165,"remaining_time":5.574171579},
{"learn":[0.3373208653],"iteration":585,"passed_time":7.869745472,"remaining_time":5.559854309},
{"learn":[0.3373048951],"iteration":586,"passed_time":7.880015733,"remaining_time":5.54420187},
{"learn":[0.3372981278],"iteration":587,"passed_time":7.8958875,"remaining_time":5.532492602},
{"learn":[0.337291758],"iteration":588,"passed_time":7.911217124,"remaining_time":5.520390896},
{"learn":[0.3372854184],"iteration":589,"passed_time":7.926314153,"remaining_time":5.508116615},
{"learn":[0.3372667633],"iteration":590,"passed_time":7.936542837,"remaining_time":5.492463656},
{"learn":[0.3372563996],"iteration":591,"passed_time":7.946775389,"remaining_time":5.476831687},
{"learn":[0.3372502207],"iteration":592,"passed_time":7.956744221,"remaining_time":5.461036927},
{"learn":[0.3372346537],"iteration":593,"passed_time":7.966892235,"remaining_time":5.445384255},
{"learn":[0.3372257773],"iteration":594,"passed_time":7.977480868,"remaining_time":5.430050003},
{"learn":[0.3372167803],"iteration":595,"passed_time":7.987824375,"remaining_time":5.414565516},
{"learn":[0.3371897371],"iteration":596,"passed_time":7.998616326,"remaining_time":5.399400971},
{"learn":[0.3371739037],"iteration":597,"passed_time":8.011406971,"remaining_time":5.385594652},
{"learn":[0.3371536477],"iteration":598,"passed_time":8.021958134,"remaining_time":5.370292507},
{"learn":[0.3371439106],"iteration":599,"passed_time":8.03216603,"remaining_time":5.354777353},
{"learn":[0.3371294403],"iteration":600,"passed_time":8.042377322,"remaining_time":5.339282115},
{"learn":[0.3371266711],"iteration":601,"passed_time":8.05215585,"remaining_time":5.323518319},
{"learn":[0.3371141034],"iteration":602,"passed_time":8.062041938,"remaining_time":5.307845189},
{"learn":[0.3371060365],"iteration":603,"passed_time":8.083058315,"remaining_time":5.299488564},
{"learn":[0.3371007612],"iteration":604,"passed_time":8.110798154,"remaining_time":5.295479786},
{"learn":[0.3370767981],"iteration":605,"passed_time":8.124801794,"remaining_time":5.282461892},
{"learn":[0.3370660853],"iteration":606,"passed_time":8.136562785,"remaining_time":5.267988755},
{"learn":[0.3370401798],"iteration":607,"passed_time":8.149163326,"remaining_time":5.254065828},
{"learn":[0.3370265367],"iteration":608,"passed_time":8.160935876,"remaining_time":5.239615644},
{"learn":[0.3370147438],"iteration":609,"passed_time":8.174336473,"remaining_time":5.226215122},
{"learn":[0.3370032536],"iteration":610,"passed_time":8.184846971,"remaining_time":5.210974586},
{"learn":[0.3369969882],"iteration":611,"passed_time":8.194786128,"remaining_time":5.195387284},
{"learn":[0.3369802438],"iteration":612,"passed_time":8.206194825,"remaining_time":5.180746162},
{"learn":[0.3369796467],"iteration":613,"passed_time":8.216819936,"remaining_time":5.165622956},
{"learn":[0.3369707544],"iteration":614,"passed_time":8.228897696,"remaining_time":5.151423761},
{"learn":[0.3369389046],"iteration":615,"passed_time":8.239454019,"remaining_time":5.136283025},
{"learn":[0.3369238505],"iteration":616,"passed_time":8.250880228,"remaining_time":5.121697127},
{"learn":[0.3369136929],"iteration":617,"passed_time":8.263380012,"remaining_time":5.107785056},
{"learn":[0.3369036992],"iteration":618,"passed_time":8.273884679,"remaining_time":5.092649536},
{"learn":[0.3368972678],"iteration":619,"passed_time":8.283915365,"remaining_time":5.077238449},
{"learn":[0.3368786394],"iteration":620,"passed_time":8.293999881,"remaining_time":5.061877544},
{"learn":[0.3368573495],"iteration":621,"passed_time":8.304162873,"remaining_time":5.046581296},
{"learn":[0.3368449181],"iteration":622,"passed_time":8.314305868,"remaining_time":5.031289426},
{"learn":[0.3368410551],"iteration":623,"passed_time":8.324732661,"remaining_time":5.016185065},
{"learn":[0.3368171911],"iteration":624,"passed_time":8.335149885,"remaining_time":5.001089931},
{"learn":[0.3368038072],"iteration":625,"passed_time":8.345069736,"remaining_time":4.98571259},
{"learn":[0.3367942208],"iteration":626,"passed_time":8.354954712,"remaining_time":4.97033191},
{"learn":[0.3367763546],"iteration":627,"passed_time":8.36516975,"remaining_time":4.955164247},
{"learn":[0.3367635713],"iteration":628,"passed_time":8.375275506,"remaining_time":4.939947874},
{"learn":[0.3367455125],"iteration":629,"passed_time":8.385265517,"remaining_time":4.924679748},
{"learn":[0.3367252879],"iteration":630,"passed_time":8.39533713,"remaining_time":4.909476071},
{"learn":[0.336715197],"iteration":631,"passed_time":8.405318735,"remaining_time":4.894236226},
{"learn":[0.3367074682],"iteration":632,"passed_time":8.415124694,"remaining_time":4.878911158},
{"learn":[0.3366926844],"iteration":633,"passed_time":8.425379978,"remaining_time":4.863862889},
{"learn":[0.3366825847],"iteration":634,"passed_time":8.435426493,"remaining_time":4.848709717},
{"learn":[0.3366734435],"iteration":635,"passed_time":8.445135482,"remaining_time":4.833379427},
{"learn":[0.3366524034],"iteration":636,"passed_time":8.455418558,"remaining_time":4.818393935},
{"learn":[0.336642185],"iteration":637,"passed_time":8.465510808,"remaining_time":4.80331491},
{"learn":[0.3366196663],"iteration":638,"passed_time":8.476544929,"remaining_time":4.788783599},
{"learn":[0.3365987446],"iteration":639,"passed_time":8.490999575,"remaining_time":4.776187261},
{"learn":[0.3365913908],"iteration":640,"passed_time":8.504120543,"remaining_time":4.762838182},
{"learn":[0.3365755558],"iteration":641,"passed_time":8.531920506,"remaining_time":4.757675298},
{"learn":[0.3365643727],"iteration":642,"passed_time":8.546245261,"remaining_time":4.744960432},
{"learn":[0.3365611465],"iteration":643,"passed_time":8.56050266,"remaining_time":4.732203334},
{"learn":[0.3365569358],"iteration":644,"passed_time":8.577314403,"remaining_time":4.720847462},
{"learn":[0.3365511294],"iteration":645,"passed_time":8.591491646,"remaining_time":4.708031026},
{"learn":[0.3365428374],"iteration":646,"passed_time":8.60153174,"remaining_time":4.692953175},
{"learn":[0.3365259832],"iteration":647,"passed_time":8.611490152,"remaining_time":4.677846502},
{"learn":[0.3365093002],"iteration":648,"passed_time":8.621719227,"remaining_time":4.662902078},
{"learn":[0.3364839033],"iteration":649,"passed_time":8.63196359,"remaining_time":4.647980395},
{"learn":[0.3364644446],"iteration":650,"passed_time":8.647385934,"remaining_time":4.635848988},
{"learn":[0.3364448546],"iteration":651,"passed_time":8.658564191,"remaining_time":4.621442237},
{"learn":[0.3364241411],"iteration":652,"passed_time":8.670116885,"remaining_time":4.607244348},
{"learn":[0.336404335],"iteration":653,"passed_time":8.680818358,"remaining_time":4.592604208},
{"learn":[0.3363970365],"iteration":654,"passed_time":8.692150272,"remaining_time":4.578308159},
{"learn":[0.3363777006],"iteration":655,"passed_time":8.703947902,"remaining_time":4.564265363},
{"learn":[0.3363565899],"iteration":656,"passed_time":8.715134225,"remaining_time":4.549910258},
{"learn":[0.3363445276],"iteration":657,"passed_time":8.725780525,"remaining_time":4.535284103},
{"learn":[0.3363436632],"iteration":658,"passed_time":8.735371054,"remaining_time":4.520123717},
{"learn":[0.3363303148],"iteration":659,"passed_time":8.74710222,"remaining_time":4.506082962},
{"learn":[0.33631245],"iteration":660,"passed_time":8.758317798,"remaining_time":4.491784771},
{"learn":[0.3362981379],"iteration":661,"passed_time":8.770089219,"remaining_time":4.477779692},
{"learn":[0.3362774112],"iteration":662,"passed_time":8.780619173,"remaining_time":4.463150319},
{"learn":[0.3362710495],"iteration":663,"passed_time":8.790557979,"remaining_time":4.448234158},
{"learn":[0.3362592847],"iteration":664,"passed_time":8.80052136,"remaining_time":4.433345347},
{"learn":[0.3362414256],"iteration":665,"passed_time":8.811071031,"remaining_time":4.418765352},
{"learn":[0.3362304288],"iteration":666,"passed_time":8.82127005,"remaining_time":4.404022379},
{"learn":[0.3362284374],"iteration":667,"passed_time":8.83091513,"remaining_time":4.3890177},
{"learn":[0.3362189684],"iteration":668,"passed_time":8.841719575,"remaining_time":4.374602659},
{"learn":[0.3362105271],"iteration":669,"passed_time":8.8587571,"remaining_time":4.363268422},
{"learn":[0.336195724],"iteration":670,"passed_time":8.869077354,"remaining_time":4.348623621},
{"learn":[0.3361814544],"iteration":671,"passed_time":8.879453141,"remaining_time":4.334018795},
{"learn":[0.3361735902],"iteration":672,"passed_time":8.889821956,"remaining_time":4.31942315},
{"learn":[0.3361696803],"iteration":673,"passed_time":8.899543068,"remaining_time":4.304526766},
{"learn":[0.3361574802],"iteration":674,"passed_time":8.909619249,"remaining_time":4.289816675},
{"learn":[0.3361421531],"iteration":675,"passed_time":8.919779516,"remaining_time":4.275160596},
{"learn":[0.3361326682],"iteration":676,"passed_time":8.929861999,"remaining_time":4.260480688},
{"learn":[0.3361256841],"iteration":677,"passed_time":8.940281077,"remaining_time":4.245974199},
{"learn":[0.3361249523],"iteration":678,"passed_time":8.949947577,"remaining_time":4.231123965},
{"learn":[0.3361103833],"iteration":679,"passed_time":8.960436044,"remaining_time":4.216675785},
{"learn":[0.3360963014],"iteration":680,"passed_time":8.972952741,"remaining_time":4.203189316},
{"learn":[0.336093497],"iteration":681,"passed_time":8.986271116,"remaining_time":4.190079494},
{"learn":[0.336084832],"iteration":682,"passed_time":8.996947282,"remaining_time":4.175742735},
{"learn":[0.3360777494],"iteration":683,"passed_time":9.006556996,"remaining_time":4.160923992},
{"learn":[0.3360677217],"iteration":684,"passed_time":9.016836114,"remaining_time":4.146428286},
{"learn":[0.3360527003],"iteration":685,"passed_time":9.026822177,"remaining_time":4.131810734},
{"learn":[0.3360365914],"iteration":686,"passed_time":9.036936139,"remaining_time":4.117264937},
{"learn":[0.336020642],"iteration":687,"passed_time":9.048579862,"remaining_time":4.103425752},
{"learn":[0.3360117892],"iteration":688,"passed_time":9.062320973,"remaining_time":4.090539655},
{"learn":[0.3360092227],"iteration":689,"passed_time":9.072387465,"remaining_time":4.076000166},
{"learn":[0.335998402],"iteration":690,"passed_time":9.082353962,"remaining_time":4.061428907},
{"learn":[0.3359743767],"iteration":691,"passed_time":9.093527502,"remaining_time":4.047408195},
{"learn":[0.3359588466],"iteration":692,"passed_time":9.108292976,"remaining_time":4.034986931},
{"learn":[0.3359444817],"iteration":693,"passed_time":9.122920793,"remaining_time":4.022498217},
{"learn":[0.335942359],"iteration":694,"passed_time":9.148533067,"remaining_time":4.014823864},
{"learn":[0.3359320526],"iteration":695,"passed_time":9.166583373,"remaining_time":4.003795037},
{"learn":[0.3359098688],"iteration":696,"passed_time":9.177005176,"remaining_time":3.989429797},
{"learn":[0.3359014107],"iteration":697,"passed_time":9.188672053,"remaining_time":3.975614556},
{"learn":[0.3358928439],"iteration":698,"passed_time":9.198814948,"remaining_time":3.961149212},
{"learn":[0.3358888154],"iteration":699,"passed_time":9.209338059,"remaining_time":3.946859168},
{"learn":[0.3358801016],"iteration":700,"passed_time":9.219315326,"remaining_time":3.932347051},
{"learn":[0.335873765],"iteration":701,"passed_time":9.230090195,"remaining_time":3.918186436},
{"learn":[0.3358717846],"iteration":702,"passed_time":9.241292941,"remaining_time":3.904216221},
{"learn":[0.3358650962],"iteration":703,"passed_time":9.25798277,"remaining_time":3.892560937},
{"learn":[0.335845907],"iteration":704,"passed_time":9.282352646,"remaining_time":3.884105008},
{"learn":[0.3358318154],"iteration":705,"passed_time":9.292946308,"remaining_time":3.86986716},
{"learn":[0.3358194618],"iteration":706,"passed_time":9.303416742,"remaining_time":3.855588551},
{"learn":[0.3358141361],"iteration":707,"passed_time":9.313801746,"remaining_time":3.841285466},
{"learn":[0.335809694],"iteration":708,"passed_time":9.323635988,"remaining_time":3.82676738},
{"learn":[0.3357977088],"iteration":709,"passed_time":9.335428748,"remaining_time":3.813062446},
{"learn":[0.3357923223],"iteration":710,"passed_time":9.345222815,"remaining_time":3.798550483},
{"learn":[0.3357821002],"iteration":711,"passed_time":9.355372042,"remaining_time":3.784195433},
{"learn":[0.3357703552],"iteration":712,"passed_time":9.365263489,"remaining_time":3.769748417},
{"learn":[0.3357509467],"iteration":713,"passed_time":9.375358255,"remaining_time":3.755395604},
{"learn":[0.3357354632],"iteration":714,"passed_time":9.385472988,"remaining_time":3.741062659},
{"learn":[0.3357326329],"iteration":715,"passed_time":9.39559831,"remaining_time":3.726745698},
{"learn":[0.3357160204],"iteration":716,"passed_time":9.406174029,"remaining_time":3.712618201},
{"learn":[0.3357082058],"iteration":717,"passed_time":9.416166153,"remaining_time":3.698271386},
{"learn":[0.3357060229],"iteration":718,"passed_time":9.426461241,"remaining_time":3.684055089},
{"learn":[0.3356862453],"iteration":719,"passed_time":9.436616329,"remaining_time":3.669795239},
{"learn":[0.3356784926],"iteration":720,"passed_time":9.446860942,"remaining_time":3.655581419},
{"learn":[0.3356729763],"iteration":721,"passed_time":9.456824705,"remaining_time":3.641270454},
{"learn":[0.3356677003],"iteration":722,"passed_time":9.469275498,"remaining_time":3.627924361},
{"learn":[0.3356581156],"iteration":723,"passed_time":9.48012774,"remaining_time":3.613971349},
{"learn":[0.3356446988],"iteration":724,"passed_time":9.491766474,"remaining_time":3.600325214},
{"learn":[0.3356248555],"iteration":725,"passed_time":9.501765882,"remaining_time":3.586065912},
{"learn":[0.3356014891],"iteration":726,"passed_time":9.512176605,"remaining_time":3.571972783},
{"learn":[0.335591391],"iteration":727,"passed_time":9.522024502,"remaining_time":3.557679484},
{"learn":[0.3355846603],"iteration":728,"passed_time":9.531917432,"remaining_time":3.543415122},
{"learn":[0.335575447],"iteration":729,"passed_time":9.541583261,"remaining_time":3.52907874},
{"learn":[0.3355574688],"iteration":730,"passed_time":9.5520404,"remaining_time":3.51504633},
{"learn":[0.3355378287],"iteration":731,"passed_time":9.562337,"remaining_time":3.500964913},
{"learn":[0.3355167191],"iteration":732,"passed_time":9.574670626,"remaining_time":3.487635821},
{"learn":[0.335512052],"iteration":733,"passed_time":9.584291801,"remaining_time":3.473326457},
{"learn":[0.3355010506],"iteration":734,"passed_time":9.5943292,"remaining_time":3.459179916},
{"learn":[0.3354807323],"iteration":735,"passed_time":9.604570518,"remaining_time":3.445117686},
{"learn":[0.3354678979],"iteration":736,"passed_time":9.614533829,"remaining_time":3.430966617},
{"learn":[0.3354585166],"iteration":737,"passed_time":9.628979829,"remaining_time":3.418418313},
{"learn":[0.3354426398],"iteration":738,"passed_time":9.639463687,"remaining_time":3.404465524},
{"learn":[0.3354246887],"iteration":739,"passed_time":9.651241831,"remaining_time":3.390976859},
{"learn":[0.3354227811],"iteration":740,"passed_time":9.661356082,"remaining_time":3.376911235},
{"learn":[0.3354134135],"iteration":741,"passed_time":9.672211862,"remaining_time":3.363114098},
{"learn":[0.335397441],"iteration":742,"passed_time":9.68369102,"remaining_time":3.349540501},
{"learn":[0.3353775558],"iteration":743,"passed_time":9.69610276,"remaining_time":3.336293423},
{"learn":[0.3353727688],"iteration":744,"passed_time":9.70617823,"remaining_time":3.322248924},
{"learn":[0.335365716],"iteration":745,"passed_time":9.716517389,"remaining_time":3.308304848},
{"learn":[0.3353624289],"iteration":746,"passed_time":9.728227997,"remaining_time":3.294834917},
{"learn":[0.3353499645],"iteration":747,"passed_time":9.739242611,"remaining_time":3.281135211},
{"learn":[0.3353265122],"iteration":748,"passed_time":9.749616265,"remaining_time":3.26722788},
{"learn":[0.3353195224],"iteration":749,"passed_time":9.764347186,"remaining_time":3.254782395},
{"learn":[0.3353098425],"iteration":750,"passed_time":9.780924977,"remaining_time":3.242943168},
{"learn":[0.3352964889],"iteration":751,"passed_time":9.804889148,"remaining_time":3.233527272},
{"learn":[0.3352845593],"iteration":752,"passed_time":9.823833766,"remaining_time":3.222426216},
{"learn":[0.335278806],"iteration":753,"passed_time":9.853872679,"remaining_time":3.214923978},
{"learn":[0.335265343],"iteration":754,"passed_time":9.872899518,"remaining_time":3.203788585},
{"learn":[0.3352558422],"iteration":755,"passed_time":9.899803496,"remaining_time":3.195174673},
{"learn":[0.3352527722],"iteration":756,"passed_time":9.916535994,"remaining_time":3.183247353},
{"learn":[0.3352402787],"iteration":757,"passed_time":9.939643905,"remaining_time":3.173342777},
{"learn":[0.3352258312],"iteration":758,"passed_time":9.964379835,"remaining_time":3.163920343},
{"learn":[0.3352183224],"iteration":759,"passed_time":9.995804298,"remaining_time":3.156569778},
{"learn":[0.3352119319],"iteration":760,"passed_time":10.01535545,"remaining_time":3.145427009},
{"learn":[0.3351968083],"iteration":761,"passed_time":10.03088224,"remaining_time":3.133005214},
{"learn":[0.3351929009],"iteration":762,"passed_time":10.04075624,"remaining_time":3.118819434},
{"learn":[0.3351807238],"iteration":763,"passed_time":10.05094917,"remaining_time":3.104743462},
{"learn":[0.3351767232],"iteration":764,"passed_time":10.06077862,"remaining_time":3.09056598},
{"learn":[0.335155239],"iteration":765,"passed_time":10.0717558,"remaining_time":3.076750467},
{"learn":[0.3351415126],"iteration":766,"passed_time":10.08302492,"remaining_time":3.063031038},
{"learn":[0.335124673],"iteration":767,"passed_time":10.09324943,"remaining_time":3.049002431},
{"learn":[0.3351241446],"iteration":768,"passed_time":10.1025061,"remaining_time":3.034692991},
{"learn":[0.335117404],"iteration":769,"passed_time":10.11687361,"remaining_time":3.021923285},
{"learn":[0.3351064969],"iteration":770,"passed_time":10.12816876,"remaining_time":3.008236896},
{"learn":[0.3350904015],"iteration":771,"passed_time":10.14121307,"remaining_time":2.99507329},
{"learn":[0.3350702502],"iteration":772,"passed_time":10.1515673,"remaining_time":2.981120021},
{"learn":[0.3350643965],"iteration":773,"passed_time":10.16137724,"remaining_time":2.967017128},
{"learn":[0.335055527],"iteration":774,"passed_time":10.17300234,"remaining_time":2.953452293},
{"learn":[0.3350251885],"iteration":775,"passed_time":10.18357179,"remaining_time":2.939587733},
{"learn":[0.3350140612],"iteration":776,"passed_time":10.19478759,"remaining_time":2.925917158},
{"learn":[0.3349927108],"iteration":777,"passed_time":10.20451887,"remaining_time":2.911829291},
{"learn":[0.3349881164],"iteration":778,"passed_time":10.21650422,"remaining_time":2.898392082},
{"learn":[0.3349726554],"iteration":779,"passed_time":10.22744398,"remaining_time":2.884663687},
{"learn":[0.3349672828],"iteration":780,"passed_time":10.23790272,"remaining_time":2.87080755},
{"learn":[0.3349480831],"iteration":781,"passed_time":10.24807506,"remaining_time":2.85688026},
{"learn":[0.3349320922],"iteration":782,"passed_time":10.25814189,"remaining_time":2.84293332},
{"learn":[0.3349182637],"iteration":783,"passed_time":10.26833971,"remaining_time":2.82903237},
{"learn":[0.3349055846],"iteration":784,"passed_time":10.27821218,"remaining_time":2.815051742},
{"learn":[0.3348932019],"iteration":785,"passed_time":10.28834611,"remaining_time":2.801152759},
{"learn":[0.334876217],"iteration":786,"passed_time":10.298721,"remaining_time":2.787328555},
{"learn":[0.3348711462],"iteration":787,"passed_time":10.30862273,"remaining_time":2.77338581},
{"learn":[0.334863814],"iteration":788,"passed_time":10.31868101,"remaining_time":2.759495176},
{"learn":[0.3348532464],"iteration":789,"passed_time":10.32893782,"remaining_time":2.745667016},
{"learn":[0.3348479437],"iteration":790,"passed_time":10.3385087,"remaining_time":2.731666648},
{"learn":[0.3348376224],"iteration":791,"passed_time":10.3484506,"remaining_time":2.717774906},
{"learn":[0.3348346788],"iteration":792,"passed_time":10.35804069,"remaining_time":2.70380129},
{"learn":[0.3348237507],"iteration":793,"passed_time":10.36785953,"remaining_time":2.689898066},
{"learn":[0.3348146651],"iteration":794,"passed_time":10.37807682,"remaining_time":2.676107859},
{"learn":[0.3348082956],"iteration":795,"passed_time":10.38793849,"remaining_time":2.662235492},
{"learn":[0.3347907981],"iteration":796,"passed_time":10.3981184,"remaining_time":2.648454248},
{"learn":[0.3347776094],"iteration":797,"passed_time":10.40814202,"remaining_time":2.634642466},
{"learn":[0.334753148],"iteration":798,"passed_time":10.4182848,"remaining_time":2.620870144},
{"learn":[0.3347443647],"iteration":799,"passed_time":10.42876508,"remaining_time":2.607191271},
{"learn":[0.3347368877],"iteration":800,"passed_time":10.44086404,"remaining_time":2.593922527},
{"learn":[0.3347222797],"iteration":801,"passed_time":10.45278263,"remaining_time":2.58061217},
{"learn":[0.3347111301],"iteration":802,"passed_time":10.46387046,"remaining_time":2.56710147},
{"learn":[0.3346953439],"iteration":803,"passed_time":10.4738383,"remaining_time":2.553323764},
{"learn":[0.3346809828],"iteration":804,"passed_time":10.48411034,"remaining_time":2.539629213},
{"learn":[0.3346798073],"iteration":805,"passed_time":10.49379468,"remaining_time":2.525801698},
{"learn":[0.3346572225],"iteration":806,"passed_time":10.50308655,"remaining_time":2.511890587},
{"learn":[0.334653508],"iteration":807,"passed_time":10.51337608,"remaining_time":2.498227978},
{"learn":[0.3346424076],"iteration":808,"passed_time":10.52402952,"remaining_time":2.484659627},
{"learn":[0.3346331485],"iteration":809,"passed_time":10.55050835,"remaining_time":2.4748106},
{"learn":[0.3346291656],"iteration":810,"passed_time":10.57663369,"remaining_time":2.464838184},
{"learn":[0.3346182489],"iteration":811,"passed_time":10.59321145,"remaining_time":2.452615458},
{"learn":[0.3346139679],"iteration":812,"passed_time":10.60713419,"remaining_time":2.439771333},
{"learn":[0.3346011561],"iteration":813,"passed_time":10.61826402,"remaining_time":2.426286373},
{"learn":[0.3345994309],"iteration":814,"passed_time":10.63153013,"remaining_time":2.413292115},
{"learn":[0.3345947681],"iteration":815,"passed_time":10.64141518,"remaining_time":2.399534794},
{"learn":[0.3345761871],"iteration":816,"passed_time":10.65156889,"remaining_time":2.385847132},
{"learn":[0.3345538116],"iteration":817,"passed_time":10.66320842,"remaining_time":2.372498694},
{"learn":[0.3345537273],"iteration":818,"passed_time":10.67468731,"remaining_time":2.35911893},
{"learn":[0.3345474758],"iteration":819,"passed_time":10.68479947,"remaining_time":2.345443786},
{"learn":[0.3345436359],"iteration":820,"passed_time":10.69436483,"remaining_time":2.331658106},
{"learn":[0.3345257827],"iteration":821,"passed_time":10.7064444,"remaining_time":2.318427132},
{"learn":[0.3345059947],"iteration":822,"passed_time":10.71748112,"remaining_time":2.304974676},
{"learn":[0.3344838698],"iteration":823,"passed_time":10.72853147,"remaining_time":2.291530994},
{"learn":[0.3344681718],"iteration":824,"passed_time":10.73885723,"remaining_time":2.277939412},
{"learn":[0.3344514641],"iteration":825,"passed_time":10.74906563,"remaining_time":2.264331017},
{"learn":[0.3344398614],"iteration":826,"passed_time":10.75896943,"remaining_time":2.250667125},
{"learn":[0.3344332961],"iteration":827,"passed_time":10.76909519,"remaining_time":2.237058421},
{"learn":[0.3344270928],"iteration":828,"passed_time":10.77895557,"remaining_time":2.22340338},
{"learn":[0.3344177619],"iteration":829,"passed_time":10.7888819,"remaining_time":2.209770991},
{"learn":[0.3344035323],"iteration":830,"passed_time":10.79899791,"remaining_time":2.196186098},
{"learn":[0.3343821268],"iteration":831,"passed_time":10.80952556,"remaining_time":2.182692662},
{"learn":[0.3343632704],"iteration":832,"passed_time":10.82470968,"remaining_time":2.170139875},
{"learn":[0.3343481483],"iteration":833,"passed_time":10.83727292,"remaining_time":2.157059118},
{"learn":[0.3343324222],"iteration":834,"passed_time":10.84770426,"remaining_time":2.143558327},
{"learn":[0.3343239685],"iteration":835,"passed_time":10.85810116,"remaining_time":2.130058122},
{"learn":[0.3343168941],"iteration":836,"passed_time":10.86812235,"remaining_time":2.116492165},
{"learn":[0.3343062272],"iteration":837,"passed_time":10.8785125,"remaining_time":2.103005996},
{"learn":[0.3342939882],"iteration":838,"passed_time":10.88868144,"remaining_time":2.089484759},
{"learn":[0.334281676],"iteration":839,"passed_time":10.89879773,"remaining_time":2.075961472},
{"learn":[0.3342656026],"iteration":840,"passed_time":10.90877005,"remaining_time":2.062419069},
{"learn":[0.3342542143],"iteration":841,"passed_time":10.9186138,"remaining_time":2.048861021},
{"learn":[0.3342421486],"iteration":842,"passed_time":10.93190536,"remaining_time":2.035953905},
{"learn":[0.334235166],"iteration":843,"passed_time":10.94190469,"remaining_time":2.02243736},
{"learn":[0.3342103049],"iteration":844,"passed_time":10.95743676,"remaining_time":2.009944021},
{"learn":[0.3341999739],"iteration":845,"passed_time":10.96761542,"remaining_time":1.996469},
{"learn":[0.3341804021],"iteration":846,"passed_time":10.97921505,"remaining_time":1.983258444},
{"learn":[0.3341697028],"iteration":847,"passed_time":10.98942015,"remaining_time":1.969801725},
{"learn":[0.3341531834],"iteration":848,"passed_time":10.99970529,"remaining_time":1.9563669},
{"learn":[0.3341415823],"iteration":849,"passed_time":11.00992505,"remaining_time":1.942927951},
{"learn":[0.334130441],"iteration":850,"passed_time":11.02012488,"remaining_time":1.929493074},
{"learn":[0.3341205685],"iteration":851,"passed_time":11.03011364,"remaining_time":1.916029131},
{"learn":[0.3341118254],"iteration":852,"passed_time":11.04069406,"remaining_time":1.902675296},
{"learn":[0.3340955732],"iteration":853,"passed_time":11.05153565,"remaining_time":1.889372606},
{"learn":[0.3340833162],"iteration":854,"passed_time":11.06220457,"remaining_time":1.876046388},
{"learn":[0.3340638146],"iteration":855,"passed_time":11.07256535,"remaining_time":1.862674544},
{"learn":[0.3340507192],"iteration":856,"passed_time":11.08293802,"remaining_time":1.849311711},
{"learn":[0.3340493634],"iteration":857,"passed_time":11.09663018,"remaining_time":1.836505227},
{"learn":[0.3340329274],"iteration":858,"passed_time":11.10687089,"remaining_time":1.823130147},
{"learn":[0.3340156243],"iteration":859,"passed_time":11.11966486,"remaining_time":1.810178001},
{"learn":[0.3340089731],"iteration":860,"passed_time":11.12955462,"remaining_time":1.796757366},
{"learn":[0.3340025107],"iteration":861,"passed_time":11.13927511,"remaining_time":1.783317825},
{"learn":[0.3339921108],"iteration":862,"passed_time":11.15114611,"remaining_time":1.770228294},
{"learn":[0.3339856992],"iteration":863,"passed_time":11.16304565,"remaining_time":1.757146075},
{"learn":[0.3339769784],"iteration":864,"passed_time":11.17347911,"remaining_time":1.74383778},
{"learn":[0.3339673473],"iteration":865,"passed_time":11.1835969,"remaining_time":1.73048728},
{"learn":[0.3339614469],"iteration":866,"passed_time":11.19598408,"remaining_time":1.717492368},
{"learn":[0.3339440791],"iteration":867,"passed_time":11.20645855,"remaining_time":1.704207983},
{"learn":[0.3339273184],"iteration":868,"passed_time":11.21853644,"remaining_time":1.691171777},
{"learn":[0.3339198202],"iteration":869,"passed_time":11.22855006,"remaining_time":1.677829319},
{"learn":[0.3339076473],"iteration":870,"passed_time":11.23846555,"remaining_time":1.664479972},
{"learn":[0.3338984499],"iteration":871,"passed_time":11.24843997,"remaining_time":1.651147152},
{"learn":[0.3338956427],"iteration":872,"passed_time":11.25969234,"remaining_time":1.638007935},
{"learn":[0.3338703631],"iteration":873,"passed_time":11.27003168,"remaining_time":1.624741409},
{"learn":[0.333859336],"iteration":874,"passed_time":11.2801797,"remaining_time":1.611454243},
{"learn":[0.3338534607],"iteration":875,"passed_time":11.29020481,"remaining_time":1.598156845},
{"learn":[0.3338281677],"iteration":876,"passed_time":11.30049608,"remaining_time":1.584904239},
{"learn":[0.3338156149],"iteration":877,"passed_time":11.31078538,"remaining_time":1.571658105},
{"learn":[0.3338088771],"iteration":878,"passed_time":11.3205808,"remaining_time":1.558350712},
{"learn":[0.3338083612],"iteration":879,"passed_time":11.33035737,"remaining_time":1.545048732},
{"learn":[0.3337958972],"iteration":880,"passed_time":11.340689,"remaining_time":1.531829728},
{"learn":[0.3337857276],"iteration":881,"passed_time":11.3509154,"remaining_time":1.518603195},
{"learn":[0.3337843818],"iteration":882,"passed_time":11.37044697,"remaining_time":1.506616416},
{"learn":[0.3337666778],"iteration":883,"passed_time":11.40013236,"remaining_time":1.49594497},
{"learn":[0.3337506389],"iteration":884,"passed_time":11.42843863,"remaining_time":1.485051348},
{"learn":[0.3337374671],"iteration":885,"passed_time":11.45602871,"remaining_time":1.474026268},
{"learn":[0.3337158902],"iteration":886,"passed_time":11.46723107,"remaining_time":1.460876112},
{"learn":[0.3337050599],"iteration":887,"passed_time":11.47762261,"remaining_time":1.447628077},
{"learn":[0.3336865856],"iteration":888,"passed_time":11.48792722,"remaining_time":1.434375614},
{"learn":[0.333670464],"iteration":889,"passed_time":11.49821893,"remaining_time":1.421128182},
{"learn":[0.3336522301],"iteration":890,"passed_time":11.50828857,"remaining_time":1.407860217},
{"learn":[0.3336485342],"iteration":891,"passed_time":11.5179106,"remaining_time":1.39454523},
{"learn":[0.3336387161],"iteration":892,"passed_time":11.5282539,"remaining_time":1.381324935},
{"learn":[0.333625448],"iteration":893,"passed_time":11.53866544,"remaining_time":1.368119169},
{"learn":[0.3336163424],"iteration":894,"passed_time":11.54861824,"remaining_time":1.354865827},
{"learn":[0.3336114572],"iteration":895,"passed_time":11.55847377,"remaining_time":1.341608562},
{"learn":[0.3336039271],"iteration":896,"passed_time":11.56896849,"remaining_time":1.32843228},
{"learn":[0.3336022838],"iteration":897,"passed_time":11.58307829,"remaining_time":1.31567259},
{"learn":[0.3335879614],"iteration":898,"passed_time":11.59457419,"remaining_time":1.302616233},
{"learn":[0.3335857681],"iteration":899,"passed_time":11.60804139,"remaining_time":1.289782377},
{"learn":[0.3335729602],"iteration":900,"passed_time":11.61827358,"remaining_time":1.276591659},
{"learn":[0.3335688962],"iteration":901,"passed_time":11.6281843,"remaining_time":1.263372574},
{"learn":[0.3335535412],"iteration":902,"passed_time":11.63999753,"remaining_time":1.250365183},
{"learn":[0.3335379505],"iteration":903,"passed_time":11.65084015,"remaining_time":1.237257361},
{"learn":[0.3335271783],"iteration":904,"passed_time":11.66139369,"remaining_time":1.224124199},
{"learn":[0.3335224057],"iteration":905,"passed_time":11.67119687,"remaining_time":1.210918881},
{"learn":[0.3335191779],"iteration":906,"passed_time":11.68440458,"remaining_time":1.19807015},
{"learn":[0.3335027133],"iteration":907,"passed_time":11.6946289,"remaining_time":1.184918346},
{"learn":[0.3334905632],"iteration":908,"passed_time":11.70611654,"remaining_time":1.171899455},
{"learn":[0.3334756683],"iteration":909,"passed_time":11.71615949,"remaining_time":1.158741048},
{"learn":[0.333465173],"iteration":910,"passed_time":11.72601053,"remaining_time":1.145570732},
{"learn":[0.3334531918],"iteration":911,"passed_time":11.73592589,"remaining_time":1.132413902},
{"learn":[0.3334458861],"iteration":912,"passed_time":11.74615533,"remaining_time":1.1192941},
{"learn":[0.3334437264],"iteration":913,"passed_time":11.75608425,"remaining_time":1.106152347},
{"learn":[0.3334401135],"iteration":914,"passed_time":11.76607171,"remaining_time":1.093023055},
{"learn":[0.3334176289],"iteration":915,"passed_time":11.77631422,"remaining_time":1.079924012},
{"learn":[0.3334018948],"iteration":916,"passed_time":11.78539298,"remaining_time":1.066725864},
{"learn":[0.3333978039],"iteration":917,"passed_time":11.79544308,"remaining_time":1.053623456},
{"learn":[0.3333952269],"iteration":918,"passed_time":11.80882727,"remaining_time":1.040821555},
{"learn":[0.3333924558],"iteration":919,"passed_time":11.81996757,"remaining_time":1.027823267},
{"learn":[0.3333842955],"iteration":920,"passed_time":11.83029073,"remaining_time":1.014758922},
{"learn":[0.3333642934],"iteration":921,"passed_time":11.84066205,"remaining_time":1.001704598},
{"learn":[0.3333435175],"iteration":922,"passed_time":11.85099212,"remaining_time":0.988652647},
{"learn":[0.3333309943],"iteration":923,"passed_time":11.86134584,"remaining_time":0.9756085319},
{"learn":[0.3333285591],"iteration":924,"passed_time":11.87114102,"remaining_time":0.9625249479},
{"learn":[0.3333187113],"iteration":925,"passed_time":11.8814674,"remaining_time":0.9494909153},
{"learn":[0.3333051558],"iteration":926,"passed_time":11.89215213,"remaining_time":0.9364909446},
{"learn":[0.3332900315],"iteration":927,"passed_time":11.90387028,"remaining_time":0.9235761427},
{"learn":[0.3332791433],"iteration":928,"passed_time":11.91404262,"remaining_time":0.9105457763},
{"learn":[0.3332693318],"iteration":929,"passed_time":11.92739395,"remaining_time":0.8977608349},
{"learn":[0.3332625061],"iteration":930,"passed_time":11.93701583,"remaining_time":0.8846982728},
{"learn":[0.3332506165],"iteration":931,"passed_time":11.94735732,"remaining_time":0.8716955984},
{"learn":[0.3332429269],"iteration":932,"passed_time":11.95737742,"remaining_time":0.8586755487},
{"learn":[0.3332320276],"iteration":933,"passed_time":11.96772663,"remaining_time":0.8456851798},
{"learn":[0.3332216009],"iteration":934,"passed_time":11.97825789,"remaining_time":0.8327131154},
{"learn":[0.333215628],"iteration":935,"passed_time":11.98810123,"remaining_time":0.8196992294},
{"learn":[0.3332024848],"iteration":936,"passed_time":11.99812856,"remaining_time":0.8067044816},
{"learn":[0.3332018703],"iteration":937,"passed_time":12.00878896,"remaining_time":0.7937579054},
{"learn":[0.3331861932],"iteration":938,"passed_time":12.01897467,"remaining_time":0.780785362},
{"learn":[0.3331718532],"iteration":939,"passed_time":12.0308712,"remaining_time":0.7679279487},
{"learn":[0.3331640711],"iteration":940,"passed_time":12.04093937,"remaining_time":0.7549579415},
{"learn":[0.3331475511],"iteration":941,"passed_time":12.05100744,"remaining_time":0.7419940885},
{"learn":[0.3331345606],"iteration":942,"passed_time":12.06109482,"remaining_time":0.7290375448},
{"learn":[0.3331242558],"iteration":943,"passed_time":12.07601836,"remaining_time":0.7163739703},
{"learn":[0.3331114767],"iteration":944,"passed_time":12.09173341,"remaining_time":0.7037516802},
{"learn":[0.3331026279],"iteration":945,"passed_time":12.10350174,"remaining_time":0.6908975623},
{"learn":[0.3330866188],"iteration":946,"passed_time":12.11390113,"remaining_time":0.6779691235},
{"learn":[0.3330813035],"iteration":947,"passed_time":12.1265933,"remaining_time":0.6651717845},
{"learn":[0.333077526],"iteration":948,"passed_time":12.13649601,"remaining_time":0.6522247592},
{"learn":[0.3330606469],"iteration":949,"passed_time":12.14898333,"remaining_time":0.6394201753},
{"learn":[0.3330476181],"iteration":950,"passed_time":12.15941345,"remaining_time":0.6265102619},
{"learn":[0.3330412181],"iteration":951,"passed_time":12.17212083,"remaining_time":0.6137203779},
{"learn":[0.333027586],"iteration":952,"passed_time":12.18262555,"remaining_time":0.6008220364},
{"learn":[0.3330202719],"iteration":953,"passed_time":12.1931387,"remaining_time":0.5879291196},
{"learn":[0.3330162536],"iteration":954,"passed_time":12.20294157,"remaining_time":0.5750077181},
{"learn":[0.3330041937],"iteration":955,"passed_time":12.21306285,"remaining_time":0.562107495},
{"learn":[0.3329820999],"iteration":956,"passed_time":12.22424588,"remaining_time":0.5492607869},
{"learn":[0.332970187],"iteration":957,"passed_time":12.23452117,"remaining_time":0.5363777546},
{"learn":[0.332954681],"iteration":958,"passed_time":12.24471718,"remaining_time":0.523496772},
{"learn":[0.332939545],"iteration":959,"passed_time":12.25482964,"remaining_time":0.5106179016},
{"learn":[0.3329296489],"iteration":960,"passed_time":12.26516896,"remaining_time":0.4977539952},
{"learn":[0.3329180005],"iteration":961,"passed_time":12.27516463,"remaining_time":0.4848817629},
{"learn":[0.3329126282],"iteration":962,"passed_time":12.28531973,"remaining_time":0.4720216302},
{"learn":[0.3329043298],"iteration":963,"passed_time":12.29535986,"remaining_time":0.4591628164},
{"learn":[0.3328951643],"iteration":964,"passed_time":12.30550928,"remaining_time":0.446313808},
{"learn":[0.3328676298],"iteration":965,"passed_time":12.31621554,"remaining_time":0.4334899879},
{"learn":[0.332859687],"iteration":966,"passed_time":12.32611853,"remaining_time":0.4206431349},
{"learn":[0.3328463427],"iteration":967,"passed_time":12.33613928,"remaining_time":0.4078062571},
{"learn":[0.3328365145],"iteration":968,"passed_time":12.34645863,"remaining_time":0.3949847446},
{"learn":[0.3328133965],"iteration":969,"passed_time":12.35689803,"remaining_time":0.3821721039},
{"learn":[0.3328005878],"iteration":970,"passed_time":12.36712311,"remaining_time":0.3693579508},
{"learn":[0.3327874733],"iteration":971,"passed_time":12.37735644,"remaining_time":0.3565493623},
{"learn":[0.3327660297],"iteration":972,"passed_time":12.38947155,"remaining_time":0.3437982857},
{"learn":[0.3327485105],"iteration":973,"passed_time":12.40137921,"remaining_time":0.3310429768},
{"learn":[0.3327402809],"iteration":974,"passed_time":12.4122591,"remaining_time":0.3182630539},
{"learn":[0.3327381401],"iteration":975,"passed_time":12.42232943,"remaining_time":0.3054671172},
{"learn":[0.3327243915],"iteration":976,"passed_time":12.43239432,"remaining_time":0.292676632},
{"learn":[0.332715391],"iteration":977,"passed_time":12.44192472,"remaining_time":0.2798796972},
{"learn":[0.3327089445],"iteration":978,"passed_time":12.45190124,"remaining_time":0.2670990051},
{"learn":[0.3326860353],"iteration":979,"passed_time":12.46237537,"remaining_time":0.2543341912},
{"learn":[0.3326749024],"iteration":980,"passed_time":12.47262886,"remaining_time":0.241569774},
{"learn":[0.3326665782],"iteration":981,"passed_time":12.4827147,"remaining_time":0.2288073977},
{"learn":[0.3326646226],"iteration":982,"passed_time":12.49270456,"remaining_time":0.2160488072},
{"learn":[0.33265854],"iteration":983,"passed_time":12.50305037,"remaining_time":0.203301632},
{"learn":[0.3326426453],"iteration":984,"passed_time":12.51334185,"remaining_time":0.1905585053},
{"learn":[0.3326331565],"iteration":985,"passed_time":12.53366425,"remaining_time":0.1779627784},
{"learn":[0.3326230563],"iteration":986,"passed_time":12.56501464,"remaining_time":0.1654966467},
{"learn":[0.3326159176],"iteration":987,"passed_time":12.58876025,"remaining_time":0.1528999221},
{"learn":[0.3325960641],"iteration":988,"passed_time":12.59919364,"remaining_time":0.1401325885},
{"learn":[0.3325815144],"iteration":989,"passed_time":12.61094007,"remaining_time":0.127383233},
{"learn":[0.3325618099],"iteration":990,"passed_time":12.62282772,"remaining_time":0.1146371841},
{"learn":[0.3325483121],"iteration":991,"passed_time":12.63347005,"remaining_time":0.101882823},
{"learn":[0.3325286293],"iteration":992,"passed_time":12.64380053,"remaining_time":0.08913051731},
{"learn":[0.3325164126],"iteration":993,"passed_time":12.65718246,"remaining_time":0.07640150378},
{"learn":[0.3325026905],"iteration":994,"passed_time":12.66733048,"remaining_time":0.06365492706},
{"learn":[0.3324945711],"iteration":995,"passed_time":12.67872963,"remaining_time":0.05091859291},
{"learn":[0.3324872067],"iteration":996,"passed_time":12.68905461,"remaining_time":0.03818170895},
{"learn":[0.3324815336],"iteration":997,"passed_time":12.69881072,"remaining_time":0.02544851848},
{"learn":[0.332470771],"iteration":998,"passed_time":12.70873467,"remaining_time":0.01272145613},
{"learn":[0.3324633218],"iteration":999,"passed_time":12.7187637,"remaining_time":0}
]}